{"Syx4wnEtvH": ["Syx4wnEtvH", "HJx8HANFDH", "rkeNfp4tPr", "Sklf1yrYDr", "ryghZJBKPS"], "BkxUvnEYDH": ["BkxUvnEYDH", "SJg5J6NtDr", "BJl07ySKvS", "SJl5Np4tPr", "rklnDgHtDS"], "HkgsPhNYPS": ["HkgsPhNYPS", "HJgExaVtwr", "Hke3gyHYwH", "ryxOUTVYDH", "HJlSmC4FPS"], "HygnDhEtvr": ["HygnDhEtvr", "B1lnbRNtwr", "SJgVHkrYDH", "rkeIIkHKvS", "S1g2skStPB"], "rkgpv2VFvr": ["rkgpv2VFvr", "SylzhkBtDB", "rke7geHtwH", "r1genAVKPB", "r1xGP6VYwH"], "H1eCw3EKvH": ["H1eCw3EKvH", "S1xitgHtvS", "S1xKd24twB", "HJli2hNKDH", "Bkl7bREtDr"], "BJxg_hVtwH": ["BJxg_hVtwH", "r1lGO0EKDH", "BylA_C4tPr", "r1lfF2NYvH", "Bkeeca4Kvr"], "rJgBd2NYPH": ["rJgBd2NYPH", "r1lGO0EKDH", "BJxWx0NYPr", "r1evOhEKvH", "rJeW1yHYwH"], "BygPO2VKPH": ["BygPO2VKPH", "rygixkHKDH", "BJxH22EKPS", "rkgz2aEKDr", "r1gixp4FPH"], "r1evOhEKvH": ["r1evOhEKvH", "BylA_C4tPr", "r1lGO0EKDH", "rJeW1yHYwH", "r1lfF2NYvH"], "S1ldO2EFPr": ["S1ldO2EFPr", "BylA_C4tPr", "BJe8pkHFwS", "r1lGO0EKDH", "BJxg_hVtwH"], "S1xKd24twB": ["S1xKd24twB", "rkgbYyHtwB", "BJl-5pNKDB", "S1xitgHtvS", "SJg5J6NtDr"], "r1eiu2VtwH": ["r1eiu2VtwH", "ByedzkrKvH", "Bke8UR4FPB", "HJgCF0VFwr", "r1ecqn4YwB"], "rJljdh4KDH": ["rJljdh4KDH", "Hke-WTVtwr", "rkl03ySYDH", "r1lfF2NYvH", "BJgMFxrYPB"], "rJlnOhVYPS": ["rJlnOhVYPS", "HkgsPhNYPS", "rJlnxkSYPS", "HJezF3VYPB", "rkgt0REKwS"], "BJl2_nVFPB": ["BJl2_nVFPB", "Hyx-jyBFPr", "HJgExaVtwr", "SJgdnAVKDH", "rJeqeCEtvH"], "Bkg0u3Etwr": ["Bkg0u3Etwr", "BkxXe0Etwr", "ByexElSYDr", "S1glGANtDr", "r1xGP6VYwH"], "HJgzt2VKPB": ["HJgzt2VKPB", "rJgsskrFwH", "SJgMK64Ywr", "SJxrKgStDH", "SJeLopEYDH"], "HJezF3VYPB": ["HJezF3VYPB", "r1evOhEKvH", "rJgqMRVYvr", "SJgaRA4FPH", "H1gfFaEYDS"], "r1lfF2NYvH": ["r1lfF2NYvH", "r1laNeBYPB", "BJxg_hVtwH", "r1evOhEKvH", "r1lGO0EKDH"], "SJg7KhVKPH": ["SJg7KhVKPH", "ByxRM0Ntvr", "ByeMPlHKPH", "rkgNKkHtvB", "r1eIiCNYwS"], "rylBK34FDS": ["rylBK34FDS", "SJlbGJrtDB", "HygpthEtvr", "SJem8lSFwB", "Syx1DkSYwB"], "BJlrF24twB": ["BJlrF24twB", "ryeFY0EFwS", "rygFWAEFwS", "B1eyO1BFPr", "BJgnXpVYwS"], "B1e9Y2NYvS": ["B1e9Y2NYvS", "SJgwzCEKwH", "rklOg6EFwS", "Hke0V1rKPS", "HyxJhCEFDS"], "H1loF2NFwr": ["H1loF2NFwr", "HJxyZkBKDr", "HygrdpVKvr", "BJxH22EKPS", "SJx9ngStPH"], "ryxnY3NYPS": ["ryxnY3NYPS", "rJgUfTEYvH", "B1l8L6EtDS", "S1g7tpEYDS", "H1laeJrKDB"], "HygpthEtvr": ["HygpthEtvr", "rkeNfp4tPr", "SJeLIgBKPS", "BJgnXpVYwS", "B1lLw6EYwB"], "HkxlcnVFwB": ["HkxlcnVFwB", "rkgU1gHtvr", "S1ltg1rFDS", "S1glGANtDr", "Hyg-JC4FDr"], "Skgxcn4YDS": ["Skgxcn4YDS", "H1eA7AEtvS", "rkl03ySYDH", "BJlS634tPr", "Syx4wnEtvH"], "ryeG924twB": ["ryeG924twB", "rJld3hEYvS", "Skln2A4YDB", "HkxdQkSYDB", "B1gZV1HYvS"], "BylEqnVFDB": ["BylEqnVFDB", "BylA_C4tPr", "r1lGO0EKDH", "S1e2agrFvS", "BJxg_hVtwH"], "BJeB5hVtvB": ["BJeB5hVtvB", "BJxVI04YvB", "HJgCF0VFwr", "H1gDNyrKDS", "S1g8K1BFwS"], "rkeIq2VYPr": ["rkeIq2VYPr", "BkxpMTEtPB", "ByxxgCEYDS", "H1l_0JBYwS", "ryxnY3NYPS"], "r1ecqn4YwB": ["r1ecqn4YwB", "r1eiu2VtwH", "Bke89JBtvB", "r1eowANFvr", "Syx4wnEtvH"], "H1xscnEKDr": ["H1xscnEKDr", "SJlHwkBYDH", "HyeaSkrYPH", "HJxdTxHYvB", "Sye_OgHFwH"], "rklp93EtwH": ["rklp93EtwH", "BklEFpEYwS", "rkeZIJBYvr", "HkgB2TNYPS", "S1evHerYPr"], "Sylgsn4Fvr": ["Sylgsn4Fvr", "SklOUpEYvB", "r1eyceSYPr", "Hkg-xgrYvH", "Hkem-lrtvH"], "rklEj2EFvB": ["rklEj2EFvB", "SylkYeHtwr", "B1x62TNtDS", "r1lOgyrKDS", "S1glGANtDr"], "H1lBj2VFPS": ["H1lBj2VFPS", "BkgXT24tDS", "rkgO66VKDS", "Hyx0slrFvH", "ryxK0JBtPr"], "HyeSin4FPB": ["HyeSin4FPB", "BJeKwTNFvB", "ryxmb1rKDS", "H1ldzA4tPr", "B1e-kxSKDH"], "B1xIj3VYvr": ["B1xIj3VYvr", "SkeuexBtDr", "S1eRbANtDB", "HJgSwyBKvr", "SyxL2TNtvr"], "r1gdj2EKPB": ["r1gdj2EKPB", "Hklso24Kwr", "rklnDgHtDS", "HklUCCVKDB", "SJgwNerKvB"], "HygOjhEYDH": ["HygOjhEYDH", "rJgUfTEYvH", "H1eqQeHFDS", "SklOUpEYvB", "Hkxzx0NtDB"], "Hklso24Kwr": ["Hklso24Kwr", "rklnDgHtDS", "r1gdj2EKPB", "SJxSOJStPr", "HklUCCVKDB"], "HJeTo2VFwH": ["HJeTo2VFwH", "ryl3ygHYDB", "SkgsACVKPH", "BJxkOlSYDH", "SJlbGJrtDB"], "BJlRs34Fvr": ["BJlRs34Fvr", "SJlHwkBYDH", "SyevYxHtDB", "SJxhNTNYwB", "HJem3yHKwH"], "rJxAo2VYwr": ["rJxAo2VYwr", "SJlHwkBYDH", "H1xscnEKDr", "SJxhNTNYwB", "Skgy464Kvr"], "BJe1334YDH": ["BJe1334YDH", "BJlS634tPr", "rkecl1rtwB", "HJe6uANtwH", "H1lBj2VFPS"], "SkxgnnNFvH": ["SkxgnnNFvH", "HJlWWJSFDH", "rkg-mA4FDr", "ByxRM0Ntvr", "H1eA7AEtvS"], "H1ebhnEYDH": ["H1ebhnEYDH", "SJxhNTNYwB", "rJxAo2VYwr", "r1xGnA4Kvr", "rkeu30EtvS"], "rygfnn4twS": ["rygfnn4twS", "H1lBj2VFPS", "BkgXT24tDS", "Hyx0slrFvH", "SJgVU0EKwS"], "BJxH22EKPS": ["BJxH22EKPS", "HJxyZkBKDr", "H1loF2NFwr", "HygrdpVKvr", "r1eowANFvr"], "Byl8hhNYPS": ["Byl8hhNYPS", "HkxQRTNYPH", "Hyl7ygStwB", "SygXPaEYvH", "H1x5wRVtvS"], "r1xPh2VtPB": ["r1xPh2VtPB", "HJl8_eHYvS", "r1lL4a4tDB", "HJli2hNKDH", "Bkg0u3Etwr"], "rJld3hEYvS": ["rJld3hEYvS", "rJeINp4KwH", "rkgU1gHtvr", "SylOlp4FvH", "rke7geHtwH"], "BJeKh3VYDH": ["BJeKh3VYDH", "H1gfFaEYDS", "HkgrZ0EYwB", "HJeVnCEKwH", "H1eqQeHFDS"], "rkxoh24FPH": ["rkxoh24FPH", "ByxaUgrFvH", "B1x62TNtDS", "Syx79eBKwr", "H1gfFaEYDS"], "HJli2hNKDH": ["HJli2hNKDH", "S1xKd24twB", "S1xitgHtvS", "r1lL4a4tDB", "HJgLLyrYwB"], "BkgWahEFvr": ["BkgWahEFvr", "HyxJhCEFDS", "SJeQEp4YDH", "HyeaSkrYPH", "H1xscnEKDr"], "BkgXT24tDS": ["BkgXT24tDS", "H1lBj2VFPS", "ryxK0JBtPr", "rJehVyrKwH", "rkgO66VKDS"], "H1lma24tPB": ["H1lma24tPB", "S1xtORNFwH", "rJxWxxSYvB", "SkgsACVKPH", "r1e_FpNFDr"], "rJx4p3NYDB": ["rJx4p3NYDB", "ByedzkrKvH", "Bkl5kxrKDr", "S1xCPJHtDB", "Syg-ET4FPS"], "BJeS62EtwH": ["BJeS62EtwH", "H1xPR3NtPB", "BylVcTNtDS", "SkgpBJrtvS", "HJlWWJSFDH"], "BJlS634tPr": ["BJlS634tPr", "BylQSxHFwr", "SkgsACVKPH", "HylxE1HKwS", "rJehVyrKwH"], "Hyg9anEFPS": ["Hyg9anEFPS", "B1gF56VYPH", "BJxt60VtPr", "H1lK_lBtvS", "BkgWahEFvr"], "HkgTTh4FDH": ["HkgTTh4FDH", "HkeryxBtPB", "HJxdTxHYvB", "Sye_OgHFwH", "rklOg6EFwS"], "rkeJRhNYDH": ["rkeJRhNYDH", "r1eIiCNYwS", "ryxjnREFwH", "Ske31kBtPr", "BJxwPJHFwS"], "S1exA2NtDB": ["S1exA2NtDB", "rkgMkCEtPB", "rkeiQlBFPB", "SJeD3CEFPH", "SkxSv6VFvS"], "rkxxA24FDr": ["rkxxA24FDr", "rJxlc0EtDr", "SyljQyBFDH", "SklKcRNYDH", "r1laNeBYPB"], "H1gzR2VKDH": ["H1gzR2VKDH", "Skl4mRNYDr", "BJeKwTNFvB", "HJgLZR4KvH", "Bkl7bREtDr"], "Syx7A3NFvH": ["Syx7A3NFvH", "HJx-3grYDB", "ByexElSYDr", "HyeSin4FPB", "BJxG_0EtDS"], "HJxNAnVtDS": ["HJxNAnVtDS", "SJxIm0VtwH", "BkglSTNFDB", "HJlxIJBFDr", "HygegyrYwH"], "HJgBA2VYwH": ["HJgBA2VYwH", "BJxg_hVtwH", "SkxgnnNFvH", "HJlWWJSFDH", "SJxpsxrYPS"], "H1xPR3NtPB": ["H1xPR3NtPB", "BJgQ4lSFPH", "HJlWWJSFDH", "BylVcTNtDS", "HklBjCEKvH"], "rkeuAhVKvB": ["rkeuAhVKvB", "r1laNeBYPB", "B1lnbRNtwr", "r1lGO0EKDH", "rkeIIkHKvS"], "ByxtC2VtPB": ["ByxtC2VtPB", "rklOg6EFwS", "SJlHwkBYDH", "H1lZJpVFvr", "HyxJhCEFDS"], "HJgK0h4Ywr": ["HJgK0h4Ywr", "HJgSwyBKvr", "Hyl9xxHYPr", "SygagpEKwB", "SyxL2TNtvr"], "SygcCnNKwr": ["SygcCnNKwr", "Hke3gyHYwH", "SJgIPJBFvH", "SylVNerFvr", "HylsTT4FvB"], "Byg9A24tvB": ["Byg9A24tvB", "rkgt0REKwS", "ryebG04YvB", "SJgwzCEKwH", "Hke0V1rKPS"], "H1lj0nNFwB": ["H1lj0nNFwB", "rkgqN1SYvr", "rkg1ngrFPr", "ryeFY0EFwS", "SJgndT4KwB"], "Hye1kTVFDS": ["Hye1kTVFDS", "S1xFl64tDr", "r1lZgyBYwS", "H1gmHaEKwB", "Syx79eBKwr"], "rylJkpEtwS": ["rylJkpEtwS", "H1lmhaVtvr", "BJliakStvH", "rkg-TJBFPB", "Sye57xStvB"], "ryxgJTEYDr": ["ryxgJTEYDr", "rkgHY0NYwr", "S1evHerYPr", "SJeD3CEFPH", "rJld3hEYvS"], "rkxZyaNtwB": ["rkxZyaNtwB", "SJeLIgBKPS", "rkgOlCVYvB", "rkgt0REKwS", "B1x6BTEKwr"], "H1lZJpVFvr": ["H1lZJpVFvr", "Hke0V1rKPS", "BJx040EFvH", "SJeQEp4YDH", "ByxtC2VtPB"], "rJgQkT4twH": ["rJgQkT4twH", "rkl8sJBYvH", "H1ebhnEYDH", "H1enKkrFDB", "HJlnC1rKPB"], "HkxBJT4YvB": ["HkxBJT4YvB", "BJg866NFvB", "B1x62TNtDS", "Bkg0u3Etwr", "Hkxzx0NtDB"], "SkeIyaVtwB": ["SkeIyaVtwB", "BJewlyStDr", "rkg-TJBFPB", "BJgy96EYvr", "r1xGP6VYwH"], "Skgvy64tvr": ["Skgvy64tvr", "SJlHwkBYDH", "H1xscnEKDr", "HyxJhCEFDS", "ByxtC2VtPB"], "HkldyTNYwH": ["HkldyTNYwH", "HJeOekHKwr", "B1l8L6EtDS", "SJgwzCEKwH", "Bke_DertPB"], "rkecJ6VFvr": ["rkecJ6VFvr", "BJg1f6EFDB", "ByeMPlHKPH", "Hyg96gBKPS", "r1eIiCNYwS"], "SJg5J6NtDr": ["SJg5J6NtDr", "S1xKd24twB", "S1evHerYPr", "rylrdxHFDr", "HJgLLyrYwB"], "rJl31TNYPr": ["rJl31TNYPr", "Skgy464Kvr", "SJxhNTNYwB", "H1xscnEKDr", "SJlHwkBYDH"], "S1efxTVYDr": ["S1efxTVYDr", "SJeYe0NtvH", "BJgza6VtPB", "HJlA0C4tPS", "SJxE8erKDH"], "HJgExaVtwr": ["HJgExaVtwr", "HklkeR4KPB", "HkgH0TEYwH", "HkgsPhNYPS", "SJgdnAVKDH"], "rklOg6EFwS": ["rklOg6EFwS", "HJxdTxHYvB", "Sye_OgHFwH", "H1xscnEKDr", "Hke0V1rKPS"], "SylOlp4FvH": ["SylOlp4FvH", "rJld3hEYvS", "rke7geHtwH", "rJeINp4KwH", "HJgC60EtwB"], "S1xFl64tDr": ["S1xFl64tDr", "ByxtC2VtPB", "Hkem-lrtvH", "H1xscnEKDr", "Hye1kTVFDS"], "r1gixp4FPH": ["r1gixp4FPH", "rkeNfp4tPr", "B1eyO1BFPr", "HJxEhREKDH", "r1g87C4KwB"], "B1esx6EYvr": ["B1esx6EYvr", "Hyx-jyBFPr", "HJeqhA4YDS", "HJlnC1rKPB", "HkgsPhNYPS"], "SygagpEKwB": ["SygagpEKwB", "HJgSwyBKvr", "SyxL2TNtvr", "HJgK0h4Ywr", "SkeuexBtDr"], "H1gax6VtDB": ["H1gax6VtDB", "BJeKwTNFvB", "SJxrKgStDH", "SkeyppEFvS", "HklXn1BKDH"], "Bylx-TNKvH": ["Bylx-TNKvH", "rkgOlCVYvB", "r1e_FpNFDr", "rJxWxxSYvB", "rJehVyrKwH"], "Hke-WTVtwr": ["Hke-WTVtwr", "rJljdh4KDH", "rJeB36NKvB", "HkxARkrFwB", "ByxY8CNtvr"], "SyxIWpVYvr": ["SyxIWpVYvr", "r1lPleBFvH", "ByxGkySKwH", "ByeNra4FDB", "SylkYeHtwr"], "SJgob6NKvH": ["SJgob6NKvH", "S1l8oANFDH", "rJeQoCNYDS", "H1e0Wp4KvH", "B1gZV1HYvS"], "B1l2bp4YwS": ["B1l2bp4YwS", "SJgndT4KwB", "rkeIIkHKvS", "r1laNeBYPB", "r1lZ7AEKvB"], "BkepbpNFwr": ["BkepbpNFwr", "rkxxA24FDr", "Bkl7bREtDr", "rJxlc0EtDr", "r1laNeBYPB"], "H1e0Wp4KvH": ["H1e0Wp4KvH", "H1lmhaVtvr", "Skl4mRNYDr", "rkg-TJBFPB", "S1lEX04tPr"], "BJg1f6EFDB": ["BJg1f6EFDB", "rkecJ6VFvr", "ByxRM0Ntvr", "ByeMPlHKPH", "Hyg96gBKPS"], "H1exf64KwH": ["H1exf64KwH", "rJld3hEYvS", "SylOlp4FvH", "BJgZGeHFPH", "rkgU1gHtvr"], "rke-f6NKvS": ["rke-f6NKvS", "rkgbYyHtwB", "rke7geHtwH", "S1xKd24twB", "r1genAVKPB"], "SJezGp4YPr": ["SJezGp4YPr", "S1ly10EKDS", "H1lj0nNFwB", "HyxnMyBKwB", "BJgQfkSYDS"], "H1emfT4twB": ["H1emfT4twB", "rylXBkrYDS", "BklEFpEYwS", "rkeZIJBYvr", "HkgB2TNYPS"], "rkeNfp4tPr": ["rkeNfp4tPr", "r1gixp4FPH", "HygpthEtvr", "r1g87C4KwB", "HJxEhREKDH"], "HJgEMpVFwB": ["HJgEMpVFwB", "SJlHwkBYDH", "HJxdTxHYvB", "H1xscnEKDr", "Sye_OgHFwH"], "rJgUfTEYvH": ["rJgUfTEYvH", "rJgsskrFwH", "ryxnY3NYPS", "SkeyppEFvS", "H1laeJrKDB"], "B1evfa4tPB": ["B1evfa4tPB", "BJxwPJHFwS", "B1gX8kBtPr", "rkeIIkHKvS", "HkeryxBtPB"], "BkxpMTEtPB": ["BkxpMTEtPB", "SJeY-1BKDS", "HyeJf1HKvS", "ByxxgCEYDS", "SygpC6Ntvr"], "B1x1ma4tDr": ["B1x1ma4tDr", "r1gfQgSFDr", "rJeqeCEtvH", "BJe-91BtvH", "HylsTT4FvB"], "rJeg7TEYwB": ["rJeg7TEYwB", "S1ldO2EFPr", "r1lGO0EKDH", "HyevIJStwH", "SJgVU0EKwS"], "BJlzm64tDH": ["BJlzm64tDH", "Hyl7ygStwB", "BJgQ4lSFPH", "H1eA7AEtvS", "HkgaETNtDB"], "rklB76EKPr": ["rklB76EKPr", "BJgnXpVYwS", "SJeLIgBKPS", "ryeFY0EFwS", "Hklz71rYvS"], "HJedXaEtvS": ["HJedXaEtvS", "S1gFvANKDS", "BJeB5hVtvB", "HyxY6JHKwr", "ryxOUTVYDH"], "SJetQpEYvB": ["SJetQpEYvB", "r1laNeBYPB", "B1lnbRNtwr", "HJlWWJSFDH", "H1eA7AEtvS"], "BJgqQ6NYvB": ["BJgqQ6NYvB", "BylQSxHFwr", "rklTmyBKPH", "SkgpBJrtvS", "BJlS634tPr"], "rygjmpVFvB": ["rygjmpVFvB", "BkglSTNFDB", "SJxIm0VtwH", "HJlxIJBFDr", "B1guLAVFDB"], "BJgnXpVYwS": ["BJgnXpVYwS", "rklB76EKPr", "ryeFY0EFwS", "SJeLIgBKPS", "rkg1ngrFPr"], "HJepXaVYDr": ["HJepXaVYDr", "SJxIm0VtwH", "HJxNAnVtDS", "rkeNfp4tPr", "SJeY-1BKDS"], "ByxT7TNFvH": ["ByxT7TNFvH", "SJgdnAVKDH", "BJedHRVtPB", "HJeO7RNKPr", "HJgExaVtwr"], "rJx1Na4Fwr": ["rJx1Na4Fwr", "BJx040EFvH", "HJxdTxHYvB", "H1lZJpVFvr", "SJxhNTNYwB"], "Skgy464Kvr": ["Skgy464Kvr", "SJlHwkBYDH", "HJxdTxHYvB", "H1xscnEKDr", "SJxhNTNYwB"], "Syg-ET4FPS": ["Syg-ET4FPS", "Bkl5kxrKDr", "BkglSTNFDB", "HJlxIJBFDr", "SJxIm0VtwH"], "SJeQEp4YDH": ["SJeQEp4YDH", "H1xscnEKDr", "Skgy464Kvr", "HJxdTxHYvB", "SJlHwkBYDH"], "r1lL4a4tDB": ["r1lL4a4tDB", "Bkl7bREtDr", "S1xKd24twB", "S1xitgHtvS", "BJgZGeHFPH"], "rJeINp4KwH": ["rJeINp4KwH", "rJld3hEYvS", "SylOlp4FvH", "Skln2A4YDB", "rkgU1gHtvr"], "HkePNpVKPB": ["HkePNpVKPB", "HJx-3grYDB", "SylVNerFvr", "Hye_V0NKwr", "HklSeREtPB"], "SJl5Np4tPr": ["SJl5Np4tPr", "rylXBkrYDS", "H1emfT4twB", "HkgB2TNYPS", "Bkeeca4Kvr"], "SJxhNTNYwB": ["SJxhNTNYwB", "SJlHwkBYDH", "Hkem-lrtvH", "SklTQCNtvS", "H1xscnEKDr"], "rJehNT4YPr": ["rJehNT4YPr", "BJeB5hVtvB", "SkgC6TNFvr", "SkgsACVKPH", "Hyg9anEFPS"], "HkgaETNtDB": ["HkgaETNtDB", "H1eA7AEtvS", "BJlzm64tDH", "Syx4wnEtvH", "H1l_0JBYwS"], "BkglSTNFDB": ["BkglSTNFDB", "HJlxIJBFDr", "SJxIm0VtwH", "HygegyrYwH", "rygjmpVFvB"], "SJxWS64FwH": ["SJxWS64FwH", "Bke89JBtvB", "H1ebhnEYDH", "HJxEhREKDH", "rkeu30EtvS"], "H1gmHaEKwB": ["H1gmHaEKwB", "HyxjOyrKvr", "HkgxW0EYDS", "r1lZgyBYwS", "rJehVyrKwH"], "BkgXHTNtvS": ["BkgXHTNtvS", "HJxEhREKDH", "B1gX8kBtPr", "B1guLAVFDB", "Skep6TVYDB"], "ByeNra4FDB": ["ByeNra4FDB", "SyxIWpVYvr", "SJx0q1rtvS", "ByxGkySKwH", "HkgH0TEYwH"], "B1x6BTEKwr": ["B1x6BTEKwr", "rkgOlCVYvB", "BkgXHTNtvS", "rkgfdeBYvH", "HyxyIgHFvr"], "B1lGU64tDr": ["B1lGU64tDr", "BJxG_0EtDS", "B1e-kxSKDH", "r1gelyrtwH", "r1laNeBYPB"], "rJxX8T4Kvr": ["rJxX8T4Kvr", "S1l8oANFDH", "Sye57xStvB", "H1ezFREtwH", "HJgcvJBFvB"], "ryg48p4tPH": ["ryg48p4tPH", "SJgzLkBKPB", "SylL0krYPS", "B1x6w0EtwH", "BJgy96EYvr"], "SkxBUpEKwH": ["SkxBUpEKwH", "SJx1URNKwH", "ryloogSKDS", "rJgsskrFwH", "rJlnOhVYPS"], "B1l8L6EtDS": ["B1l8L6EtDS", "BJgza6VtPB", "Bke_DertPB", "HJeOekHKwr", "S1lxKlSKPH"], "ryxOUTVYDH": ["ryxOUTVYDH", "Sklf1yrYDr", "SkgsACVKPH", "rkgt0REKwS", "HkgsPhNYPS"], "SklOUpEYvB": ["SklOUpEYvB", "Hkg-xgrYvH", "SylkYeHtwr", "S1g7tpEYDS", "rygeHgSFDH"], "BkeWw6VFwr": ["BkeWw6VFwr", "rklk_ySYPB", "HkeryxBtPB", "HJxdTxHYvB", "HkgTTh4FDH"], "r1xGP6VYwH": ["r1xGP6VYwH", "rklHqRVKvH", "S1xitgHtvS", "BkxXe0Etwr", "BJewlyStDr"], "SygXPaEYvH": ["SygXPaEYvH", "BJgQ4lSFPH", "HJlWWJSFDH", "HkxYzANYDB", "Hyl7ygStwB"], "SkxSv6VFvS": ["SkxSv6VFvS", "S1exA2NtDB", "H1gBhkBFDH", "Hygab1rKDS", "HJgpugrKPS"], "BygSP6Vtvr": ["BygSP6Vtvr", "Sklf1yrYDr", "BJxI5gHKDr", "ryx6WgStPB", "BJlahxHYDS"], "B1lLw6EYwB": ["B1lLw6EYwB", "BJgnXpVYwS", "rkeNfp4tPr", "Bkeb7lHtvH", "ryeFY0EFwS"], "SJxDDpEKvH": ["SJxDDpEKvH", "H1laeJrKDB", "SJxIm0VtwH", "SJeY-1BKDS", "rygjmpVFvB"], "BJeKwTNFvB": ["BJeKwTNFvB", "HyeSin4FPB", "SkeyppEFvS", "ryxmb1rKDS", "B1e-kxSKDH"], "SJe5P6EYvS": ["SJe5P6EYvS", "SylKikSYDH", "rJeXS04FPH", "Bkl7bREtDr", "rylnK6VtDH"], "HJeiDpVFPr": ["HJeiDpVFPr", "BJxH22EKPS", "BJeB5hVtvB", "B1guLAVFDB", "SkgKO0EtvS"], "ryenvpEKDr": ["ryenvpEKDr", "rkgg6xBYDH", "SkxxtgHKPS", "H1lj0nNFwB", "HklSeREtPB"], "HklRwaEKwB": ["HklRwaEKwB", "rklEj2EFvB", "B1x62TNtDS", "Hke3gyHYwH", "H1l_0JBYwS"], "BJlguT4YPr": ["BJlguT4YPr", "SJxstlHFPH", "SJem8lSFwB", "SJlbGJrtDB", "SygpC6Ntvr"], "HJlfuTEtvB": ["HJlfuTEtvB", "SJetQpEYvB", "rylwJxrYDS", "HJeO7RNKPr", "BJl07ySKvS"], "HygrdpVKvr": ["HygrdpVKvr", "H1loF2NFwr", "HJxyZkBKDr", "BylQSxHFwr", "BJxH22EKPS"], "B1eY_pVYvB": ["B1eY_pVYvB", "SklKcRNYDH", "r1gdj2EKPB", "HylpqA4FwS", "BJge3TNKwH"], "HygsuaNFwr": ["HygsuaNFwr", "rkem91rtDB", "SJeNz04tDS", "rJeW1yHYwH", "HklkeR4KPB"], "SJgndT4KwB": ["SJgndT4KwB", "rkgqN1SYvr", "rkllGyBFPH", "B1l2bp4YwS", "S1gFvANKDS"], "HJgJtT4tvB": ["HJgJtT4tvB", "ryxjnREFwH", "rJxbJeHFPS", "Byg1v1HKDB", "BJgQ4lSFPH"], "SJgMK64Ywr": ["SJgMK64Ywr", "SJeLopEYDH", "rJgsskrFwH", "HJgzt2VKPB", "B1eY_pVYvB"], "H1gfFaEYDS": ["H1gfFaEYDS", "Bke_DertPB", "Hke0V1rKPS", "S1g7tpEYDS", "SygagpEKwB"], "S1g7tpEYDS": ["S1g7tpEYDS", "S1g6xeSKDS", "SklOUpEYvB", "H1laeJrKDB", "H1gfFaEYDS"], "BklEFpEYwS": ["BklEFpEYwS", "rklp93EtwH", "HkgB2TNYPS", "rkeZIJBYvr", "S1evHerYPr"], "SkxLFaNKwB": ["SkxLFaNKwB", "rklTmyBKPH", "BylQSxHFwr", "r1eowANFvr", "ryxyCeHtPB"], "rylvYaNYDH": ["rylvYaNYDH", "S1xCPJHtDB", "S1xKd24twB", "HkxjqxBYDB", "HJl8_eHYvS"], "HygDF6NFPB": ["HygDF6NFPB", "r1lGO0EKDH", "BJxg_hVtwH", "rkeIIkHKvS", "BylA_C4tPr"], "r1e_FpNFDr": ["r1e_FpNFDr", "rkgg6xBYDH", "SkxxtgHKPS", "Skxuk1rFwB", "Hke3gyHYwH"], "rye5YaEtPr": ["rye5YaEtPr", "SJxZnR4YvB", "BkglSTNFDB", "HJxNAnVtDS", "Skep6TVYDB"], "SJlsFpVtDB": ["SJlsFpVtDB", "HkxCzeHFDB", "SJxSOJStPr", "rkxxA24FDr", "Hklso24Kwr"], "rylnK6VtDH": ["rylnK6VtDH", "HJlnC1rKPB", "ByxRM0Ntvr", "SJe5P6EYvS", "HJenn6VFvB"], "BJgy96EYvr": ["BJgy96EYvr", "rkg-TJBFPB", "Sye57xStvB", "BJewlyStDr", "S1lEX04tPr"], "Bkeeca4Kvr": ["Bkeeca4Kvr", "rkeIIkHKvS", "r1laNeBYPB", "rylXBkrYDS", "r1lGO0EKDH"], "BJl-5pNKDB": ["BJl-5pNKDB", "S1xKd24twB", "B1gZV1HYvS", "Hyg-JC4FDr", "rkgbYyHtwB"], "BylVcTNtDS": ["BylVcTNtDS", "SJxhNTNYwB", "rJxAo2VYwr", "SJlHwkBYDH", "Skxd6gSYDS"], "rJeIcTNtvS": ["rJeIcTNtvS", "Hke0K1HKwr", "SygagpEKwB", "HJlWWJSFDH", "rklk_ySYPB"], "B1gF56VYPH": ["B1gF56VYPH", "Hyg9anEFPS", "BJedHRVtPB", "HyxjNyrtPr", "ByxQB1BKwH"], "HJxK5pEYvr": ["HJxK5pEYvr", "ByeMPlHKPH", "r1eIiCNYwS", "ByxRM0Ntvr", "ByxY8CNtvr"], "SkgscaNYPS": ["SkgscaNYPS", "rkl8sJBYvH", "SJgndT4KwB", "rkllGyBFPH", "HyevIJStwH"], "H1lhqpEYPr": ["H1lhqpEYPr", "BJgQfkSYDS", "Bkl5kxrKDr", "S1xCPJHtDB", "Sye57xStvB"], "SJx-j64FDr": ["SJx-j64FDr", "rkxs0yHFPH", "rJg76kStwH", "SJlh8CEYDB", "SkgsACVKPH"], "SJg7spEYDS": ["SJg7spEYDS", "HJeVnCEKwH", "r1gfQgSFDr", "Bke_DertPB", "HylsTT4FvB"], "rylHspEKPr": ["rylHspEKPr", "rJeqeCEtvH", "HyxnMyBKwB", "Hkx6hANtwH", "B1g5sA4twr"], "SJeLopEYDH": ["SJeLopEYDH", "SJgMK64Ywr", "rJgsskrFwH", "HJgzt2VKPB", "HkxYzANYDB"], "SJeqs6EFvB": ["SJeqs6EFvB", "S1ldO2EFPr", "Hkx6hANtwH", "ryxjnREFwH", "BylA_C4tPr"], "B1gqipNYwH": ["B1gqipNYwH", "HJgLZR4KvH", "H1ezFREtwH", "ByeWogStDS", "ryxB2lBtvH"], "BJge3TNKwH": ["BJge3TNKwH", "HklUCCVKDB", "B1eY_pVYvB", "r1gdj2EKPB", "ryx1wRNFvB"], "HyxG3p4twS": ["HyxG3p4twS", "HyxjOyrKvr", "r1lZgyBYwS", "SkgGCkrKvH", "SJgVU0EKwS"], "rkgz2aEKDr": ["rkgz2aEKDr", "rkeNfp4tPr", "Syx4wnEtvH", "ryxz8CVYDH", "r1g87C4KwB"], "H1lmhaVtvr": ["H1lmhaVtvr", "H1e0Wp4KvH", "S1xKd24twB", "HJgLZR4KvH", "rkg-TJBFPB"], "HkgB2TNYPS": ["HkgB2TNYPS", "BklEFpEYwS", "rkeZIJBYvr", "S1evHerYPr", "rkgAGAVKPr"], "rJeB36NKvB": ["rJeB36NKvB", "Hke-WTVtwr", "HJxMYANtPH", "rJxWxxSYvB", "H1lj0nNFwB"], "SyxL2TNtvr": ["SyxL2TNtvr", "SygagpEKwB", "HJgK0h4Ywr", "HJgSwyBKvr", "Hyl9xxHYPr"], "BkgnhTEtDS": ["BkgnhTEtDS", "Hkem-lrtvH", "B1lj20NFDS", "SJxhNTNYwB", "ByxxgCEYDS"], "HJenn6VFvB": ["HJenn6VFvB", "ryxmb1rKDS", "BkgYPREtPr", "HyeSin4FPB", "rJeqeCEtvH"], "B1x62TNtDS": ["B1x62TNtDS", "rklEj2EFvB", "ByxaUgrFvH", "SylkYeHtwr", "rkxoh24FPH"], "SkeyppEFvS": ["SkeyppEFvS", "BJeKwTNFvB", "B1e-kxSKDH", "rJgUfTEYvH", "HyeSin4FPB"], "BkxfaTVFwH": ["BkxfaTVFwH", "rkl03ySYDH", "SJxrKgStDH", "H1laeJrKDB", "SkeyppEFvS"], "BJgza6VtPB": ["BJgza6VtPB", "B1l8L6EtDS", "HJeOekHKwr", "Bke_DertPB", "S1lxKlSKPH"], "S1lSapVtwS": ["S1lSapVtwS", "H1x5wRVtvS", "B1lPaCNtPB", "B1l8L6EtDS", "HyxjNyrtPr"], "BJg866NFvB": ["BJg866NFvB", "HkxBJT4YvB", "SkeyppEFvS", "r1gelyrtwH", "rkgU1gHtvr"], "rkgO66VKDS": ["rkgO66VKDS", "H1lBj2VFPS", "BkgXT24tDS", "Hyx0slrFvH", "rJehVyrKwH"], "HylsTT4FvB": ["HylsTT4FvB", "r1gfQgSFDr", "B1lPaCNtPB", "H1laeJrKDB", "HJeVnCEKwH"], "Skep6TVYDB": ["Skep6TVYDB", "HygegyrYwH", "B1guLAVFDB", "B1gX8kBtPr", "HJlxIJBFDr"], "SkgC6TNFvr": ["SkgC6TNFvr", "BJgqQ6NYvB", "HklkeR4KPB", "ByxT7TNFvH", "rkl8dlHYvB"], "B1elCp4KwH": ["B1elCp4KwH", "rJehVyrKwH", "H1lBj2VFPS", "BJxSI1SKDH", "H1gmHaEKwB"], "SygW0TEFwH": ["SygW0TEFwH", "Hkem-lrtvH", "BJgr4kSFDS", "Skep6TVYDB", "SJxhNTNYwB"], "HkxQRTNYPH": ["HkxQRTNYPH", "Byl8hhNYPS", "BJxSI1SKDH", "HJlA0C4tPS", "rJxtgJBKDr"], "HkgH0TEYwH": ["HkgH0TEYwH", "SJx0q1rtvS", "HJgExaVtwr", "HJx81ySKwr", "SJeq9JBFvH"], "HyxLRTVKPH": ["HyxLRTVKPH", "rklTmyBKPH", "HylxE1HKwS", "Syx4wnEtvH", "SkgsACVKPH"], "SygpC6Ntvr": ["SygpC6Ntvr", "HkxARkrFwB", "BkxpMTEtPB", "HyeYTgrFPB", "SJxzFySKwH"], "S1ly10EKDS": ["S1ly10EKDS", "SJezGp4YPr", "HJxNAnVtDS", "SJxIm0VtwH", "S1glGANtDr"], "Hyg-JC4FDr": ["Hyg-JC4FDr", "S1xKd24twB", "rJld3hEYvS", "rkgU1gHtvr", "S1glGANtDr"], "rkgMkCEtPB": ["rkgMkCEtPB", "BklEFpEYwS", "HkgB2TNYPS", "rkeZIJBYvr", "S1exA2NtDB"], "H1lmyRNFvr": ["H1lmyRNFvr", "S1esMkHYPr", "H1laeJrKDB", "BJl-5pNKDB", "ryeYpJSKwr"], "rkeS1RVtPS": ["rkeS1RVtPS", "BJgnXpVYwS", "HJepXaVYDr", "S1gEIerYwH", "BkeoaeHKDS"], "HJe_yR4Fwr": ["HJe_yR4Fwr", "rkgg6xBYDH", "HkeryxBtPB", "SkxxtgHKPS", "Hke3gyHYwH"], "B1l6y0VFPr": ["B1l6y0VFPr", "rygjHxrYDB", "HJlnC1rKPB", "H1lj0nNFwB", "B1esx6EYvr"], "Hkekl0NFPr": ["Hkekl0NFPr", "HkgsUJrtDB", "B1gdkxHFDH", "S1l-C0NtwS", "HJgK0h4Ywr"], "HklkeR4KPB": ["HklkeR4KPB", "HJgExaVtwr", "ByxdUySKvS", "S1lxKlSKPH", "Hyx-jyBFPr"], "ByxxgCEYDS": ["ByxxgCEYDS", "BkxpMTEtPB", "HkgrZ0EYwB", "BJlzm64tDH", "SJxzFySKwH"], "BJxWx0NYPr": ["BJxWx0NYPr", "r1evOhEKvH", "r1lGO0EKDH", "BylEqnVFDB", "BJxg_hVtwH"], "Hkxzx0NtDB": ["Hkxzx0NtDB", "HJloElBYvB", "r1lPleBFvH", "S1lxKlSKPH", "Hye1RJHKwB"], "BkxXe0Etwr": ["BkxXe0Etwr", "Bkg0u3Etwr", "rklHqRVKvH", "r1xGP6VYwH", "rJld3hEYvS"], "Hkx7xRVYDr": ["Hkx7xRVYDr", "rygG4AVFvH", "rkxNh1Stvr", "SyxV9ANFDH", "S1g8K1BFwS"], "HklSeREtPB": ["HklSeREtPB", "SyxrxR4KPS", "ByeUBANtvB", "rklr9kHFDB", "rkxs0yHFPH"], "SyxrxR4KPS": ["SyxrxR4KPS", "HklSeREtPB", "H1ebhnEYDH", "BJxG_0EtDS", "rkgbYyHtwB"], "BJluxREKDB": ["BJluxREKDB", "rke-f6NKvS", "BJeGlJStPr", "r1lZ7AEKvB", "S1l8oANFDH"], "rkgOlCVYvB": ["rkgOlCVYvB", "B1x6BTEKwr", "SJeLIgBKPS", "BkgXHTNtvS", "Bylx-TNKvH"], "SJeYe0NtvH": ["SJeYe0NtvH", "rygGQyrFvH", "B1l4SgHKDH", "S1efxTVYDr", "Hye1RJHKwB"], "rJeqeCEtvH": ["rJeqeCEtvH", "SklD9yrFPS", "B1x1ma4tDr", "r1gfQgSFDr", "HylsTT4FvB"], "SkxybANtDB": ["SkxybANtDB", "Sklgs0NFvr", "SJxUjlBtwB", "BJlahxHYDS", "SyxV9ANFDH"], "HkgxW0EYDS": ["HkgxW0EYDS", "HyxjOyrKvr", "r1lZgyBYwS", "H1gmHaEKwB", "SJem8lSFwB"], "Bkl7bREtDr": ["Bkl7bREtDr", "r1lL4a4tDB", "S1xKd24twB", "S1xitgHtvS", "BJeGlJStPr"], "HJxV-ANKDH": ["HJxV-ANKDH", "r1gixp4FPH", "rkeNfp4tPr", "rkgz2aEKDr", "rJg8TeSFDH"], "HkgrZ0EYwB": ["HkgrZ0EYwB", "ByxxgCEYDS", "BJeKh3VYDH", "BJlzm64tDH", "rkxNh1Stvr"], "HJgLZR4KvH": ["HJgLZR4KvH", "H1ezFREtwH", "B1gqipNYwH", "S1xKd24twB", "rke7geHtwH"], "HJe_Z04Yvr": ["HJe_Z04Yvr", "HJlA0C4tPS", "HyxY6JHKwr", "BJe-91BtvH", "SkgsACVKPH"], "rygFWAEFwS": ["rygFWAEFwS", "ByxdUySKvS", "SkgsACVKPH", "Sklf1yrYDr", "SklkDkSFPB"], "Byg5ZANtvH": ["Byg5ZANtvH", "rygixkHKDH", "SJxIm0VtwH", "HylAoJSKvH", "HJepXaVYDr"], "HJg2b0VYDr": ["HJg2b0VYDr", "ByxdUySKvS", "BJx040EFvH", "rygFWAEFwS", "SJgVU0EKwS"], "B1lnbRNtwr": ["B1lnbRNtwr", "rkeuAhVKvB", "r1lGO0EKDH", "BylA_C4tPr", "SJetQpEYvB"], "BJl6bANtwH": ["BJl6bANtwH", "BkeoaeHKDS", "H1xPR3NtPB", "BylVcTNtDS", "HJlWWJSFDH"], "S1eRbANtDB": ["S1eRbANtDB", "HkgsUJrtDB", "H1l_0JBYwS", "HJeiDpVFPr", "rylwJxrYDS"], "S1glGANtDr": ["S1glGANtDr", "rkgU1gHtvr", "S1ltg1rFDS", "Hyg-JC4FDr", "Bkg0u3Etwr"], "ryebG04YvB": ["ryebG04YvB", "Hke0V1rKPS", "H1lZJpVFvr", "BJx040EFvH", "HyxJhCEFDS"], "BkgzMCVtPB": ["BkgzMCVtPB", "H1xscnEKDr", "SJeQEp4YDH", "SyevYxHtDB", "HyeaSkrYPH"], "SJeNz04tDS": ["SJeNz04tDS", "rJgqMRVYvr", "BklEFpEYwS", "Bkg0u3Etwr", "Sklgs0NFvr"], "SJgwzCEKwH": ["SJgwzCEKwH", "H1xscnEKDr", "HyxJhCEFDS", "Hke0V1rKPS", "r1xGnA4Kvr"], "H1ldzA4tPr": ["H1ldzA4tPr", "HyeSin4FPB", "HJgfDREKDB", "BJeKwTNFvB", "ryxmb1rKDS"], "HkxYzANYDB": ["HkxYzANYDB", "ryxWIgBFPS", "rJgsskrFwH", "SygXPaEYvH", "SkeyppEFvS"], "rJgqMRVYvr": ["rJgqMRVYvr", "SJgaRA4FPH", "rylXBkrYDS", "BklEFpEYwS", "SJeNz04tDS"], "r1e9GCNKvH": ["r1e9GCNKvH", "ryl3ygHYDB", "HJeTo2VFwH", "SJlbGJrtDB", "SJem8lSFwB"], "rkgAGAVKPr": ["rkgAGAVKPr", "HkgB2TNYPS", "BklEFpEYwS", "rkeZIJBYvr", "S1evHerYPr"], "ByxRM0Ntvr": ["ByxRM0Ntvr", "SJg7KhVKPH", "BJg1f6EFDB", "HJlnC1rKPB", "ByeMPlHKPH"], "rkg-mA4FDr": ["rkg-mA4FDr", "SkxgnnNFvH", "HJlWWJSFDH", "BJgQ4lSFPH", "SJgdnAVKDH"], "r1lZ7AEKvB": ["r1lZ7AEKvB", "rkeIIkHKvS", "r1laNeBYPB", "rJg76kStwH", "Bkeeca4Kvr"], "Skl4mRNYDr": ["Skl4mRNYDr", "H1e0Wp4KvH", "HJgLLyrYwB", "H1lmhaVtvr", "SJg5J6NtDr"], "S1lEX04tPr": ["S1lEX04tPr", "B1gZV1HYvS", "HkxdQkSYDB", "BJgy96EYvr", "H1e0Wp4KvH"], "HJlSmC4FPS": ["HJlSmC4FPS", "HJeqhA4YDS", "HkgsPhNYPS", "ryxOUTVYDH", "Hke3gyHYwH"], "SJxIm0VtwH": ["SJxIm0VtwH", "HJlxIJBFDr", "BkglSTNFDB", "HygegyrYwH", "HJxNAnVtDS"], "r1g87C4KwB": ["r1g87C4KwB", "rkeNfp4tPr", "ryeFY0EFwS", "BJgnXpVYwS", "SJeLIgBKPS"], "HJeO7RNKPr": ["HJeO7RNKPr", "BJedHRVtPB", "ByxT7TNFvH", "SJgndT4KwB", "S1eALyrYDH"], "rkenmREFDr": ["rkenmREFDr", "H1lNPxHKDH", "B1guLAVFDB", "BkglSTNFDB", "HJlxIJBFDr"], "S1xnXRVFwH": ["S1xnXRVFwH", "rkgqN1SYvr", "rkg1ngrFPr", "SkgsACVKPH", "H1eCw3EKvH"], "SklTQCNtvS": ["SklTQCNtvS", "SJxhNTNYwB", "Hkem-lrtvH", "SJlHwkBYDH", "Skxd6gSYDS"], "H1eA7AEtvS": ["H1eA7AEtvS", "Hyl7ygStwB", "BJgQ4lSFPH", "BJlzm64tDH", "HkgaETNtDB"], "HJxR7R4FvS": ["HJxR7R4FvS", "Skln2A4YDB", "BJgQfkSYDS", "rklHqRVKvH", "rkeiQlBFPB"], "SJleNCNtDH": ["SJleNCNtDH", "rkg-TJBFPB", "BJgy96EYvr", "H1lmhaVtvr", "B1gZV1HYvS"], "rygG4AVFvH": ["rygG4AVFvH", "SklKcRNYDH", "rkxDoJBYPB", "H1lBj2VFPS", "HylxE1HKwS"], "HJxrVA4FDS": ["HJxrVA4FDS", "H1gB4RVKvB", "SJxpsxrYPS", "ryl3ygHYDB", "BJlRs34Fvr"], "H1gB4RVKvB": ["H1gB4RVKvB", "HklSeREtPB", "HJxrVA4FDS", "rklr9kHFDB", "ByxQB1BKwH"], "Hye_V0NKwr": ["Hye_V0NKwr", "BygXFkSYDH", "H1emfT4twB", "r1xCMyBtPS", "HJgK0h4Ywr"], "BygFVAEKDH": ["BygFVAEKDH", "SkgpBJrtvS", "BygSP6Vtvr", "Sklf1yrYDr", "SylO2yStDr"], "Byl5NREFDr": ["Byl5NREFDr", "SJxhNTNYwB", "Skxd6gSYDS", "H1xscnEKDr", "SyevYxHtDB"], "BJx040EFvH": ["BJx040EFvH", "H1lZJpVFvr", "Hke0V1rKPS", "rJx1Na4Fwr", "HyxJhCEFDS"], "rkgyS0VFvr": ["rkgyS0VFvr", "H1xscnEKDr", "SJlHwkBYDH", "SJgwzCEKwH", "SJeQEp4YDH"], "rJeXS04FPH": ["rJeXS04FPH", "SJg7KhVKPH", "SylKikSYDH", "HyxjOyrKvr", "r1gdj2EKPB"], "rylVHR4FPB": ["rylVHR4FPB", "H1lBj2VFPS", "Hyx0slrFvH", "HJem3yHKwH", "rkgO66VKDS"], "ByeUBANtvB": ["ByeUBANtvB", "BJgnXpVYwS", "ryeFY0EFwS", "rJxWxxSYvB", "ryxdEkHtPS"], "HJx8HANFDH": ["HJx8HANFDH", "SkgGjRVKDS", "ryghZJBKPS", "rkeu30EtvS", "Syx4wnEtvH"], "BJedHRVtPB": ["BJedHRVtPB", "HJeO7RNKPr", "ByxT7TNFvH", "B1gF56VYPH", "SJgndT4KwB"], "SkxJ8REYPH": ["SkxJ8REYPH", "rkeNfp4tPr", "B1lLw6EYwB", "SJlVY04FwH", "r1gixp4FPH"], "SJx1URNKwH": ["SJx1URNKwH", "SkxBUpEKwH", "BklEFpEYwS", "SJeD3CEFPH", "H1emfT4twB"], "ryxz8CVYDH": ["ryxz8CVYDH", "Hklz71rYvS", "BJgnXpVYwS", "SklTQCNtvS", "SJeLIgBKPS"], "H1gX8C4YPr": ["H1gX8C4YPr", "HylxE1HKwS", "ByeMPlHKPH", "ryxyCeHtPB", "rkgvXlrKwH"], "BJxVI04YvB": ["BJxVI04YvB", "BJeB5hVtvB", "SkxxtgHKPS", "ByxGkySKwH", "rkgg6xBYDH"], "SJgVU0EKwS": ["SJgVU0EKwS", "BkgXT24tDS", "Bkxe2AVtPS", "rkgO66VKDS", "H1lBj2VFPS"], "Bke8UR4FPB": ["Bke8UR4FPB", "r1eiu2VtwH", "B1gX8kBtPr", "B1guLAVFDB", "BkgXHTNtvS"], "B1guLAVFDB": ["B1guLAVFDB", "HygegyrYwH", "HJlxIJBFDr", "BkglSTNFDB", "Skep6TVYDB"], "ByxY8CNtvr": ["ByxY8CNtvr", "ByeMPlHKPH", "r1eIiCNYwS", "ByxRM0Ntvr", "Hyl7ygStwB"], "SJlh8CEYDB": ["SJlh8CEYDB", "Byg1v1HKDB", "B1eB5xSFvr", "rJleKgrKwS", "SJx-j64FDr"], "ryx1wRNFvB": ["ryx1wRNFvB", "HylpqA4FwS", "SJgmR0NKPr", "rkg1ngrFPr", "rkgqN1SYvr"], "rJgJDAVKvB": ["rJgJDAVKvB", "BkglSTNFDB", "SJxIm0VtwH", "HJlxIJBFDr", "rygjmpVFvB"], "SygWvAVFPr": ["SygWvAVFPr", "ryxjnREFwH", "SJgVHkrYDH", "HkxYzANYDB", "HygnDhEtvr"], "HJgfDREKDB": ["HJgfDREKDB", "SJxrKgStDH", "H1ldzA4tPr", "SJlbGJrtDB", "rylb3eBtwr"], "BkgYPREtPr": ["BkgYPREtPr", "ryxmb1rKDS", "HJenn6VFvB", "r1gelyrtwH", "HJgLZR4KvH"], "S1gFvANKDS": ["S1gFvANKDS", "SJgndT4KwB", "Hke3gyHYwH", "H1lj0nNFwB", "rkllGyBFPH"], "H1x5wRVtvS": ["H1x5wRVtvS", "B1lPaCNtPB", "Hye1RJHKwB", "HyxjNyrtPr", "r1gfQgSFDr"], "r1eowANFvr": ["r1eowANFvr", "HJxyZkBKDr", "BylQSxHFwr", "H1loF2NFwr", "rklTmyBKPH"], "B1x6w0EtwH": ["B1x6w0EtwH", "SJgzLkBKPB", "rkg-TJBFPB", "Sye57xStvB", "S1xCPJHtDB"], "r1lGO0EKDH": ["r1lGO0EKDH", "BylA_C4tPr", "BJxg_hVtwH", "SkxQp1StDH", "rkeIIkHKvS"], "BJxG_0EtDS": ["BJxG_0EtDS", "S1g6xeSKDS", "HJgLZR4KvH", "ryxmb1rKDS", "SklOUpEYvB"], "ryxQuANKPB": ["ryxQuANKPB", "H1e_cC4twS", "BkgnhTEtDS", "HJxK5pEYvr", "ByeMPlHKPH"], "SkeHuCVFDr": ["SkeHuCVFDr", "Hyl7ygStwB", "r1xMH1BtvB", "BJgQ4lSFPH", "HJeiDpVFPr"], "SkgKO0EtvS": ["SkgKO0EtvS", "r1laNeBYPB", "rkeIIkHKvS", "B1lnbRNtwr", "BylEqnVFDB"], "r1lF_CEYwS": ["r1lF_CEYwS", "HJxdTxHYvB", "rklOg6EFwS", "SJlHwkBYDH", "SJeQEp4YDH"], "S1xtORNFwH": ["S1xtORNFwH", "HyxjOyrKvr", "rJehVyrKwH", "rkeu30EtvS", "BJlS634tPr"], "HJe6uANtwH": ["HJe6uANtwH", "BJgNJgSFPS", "rkeu30EtvS", "HJx8HANFDH", "ByxdUySKvS"], "BylA_C4tPr": ["BylA_C4tPr", "r1lGO0EKDH", "BJe8pkHFwS", "BJxg_hVtwH", "r1evOhEKvH"], "rklbKA4YDS": ["rklbKA4YDS", "S1g2skStPB", "B1gHokBKwS", "H1ldzA4tPr", "HyeSin4FPB"], "HJxMYANtPH": ["HJxMYANtPH", "rJeB36NKvB", "B1x6BTEKwr", "rkllGyBFPH", "rkgfdeBYvH"], "H1ezFREtwH": ["H1ezFREtwH", "rke7geHtwH", "HJgLZR4KvH", "ByeWogStDS", "S1l8oANFDH"], "SJlVY04FwH": ["SJlVY04FwH", "rkeNfp4tPr", "BJgQfkSYDS", "Hkx7_1rKwS", "BJgnXpVYwS"], "rkgHY0NYwr": ["rkgHY0NYwr", "ryxgJTEYDr", "SJg5J6NtDr", "HJgLZR4KvH", "BJe-91BtvH"], "rJlUt0EYwS": ["rJlUt0EYwS", "BkxRRkSKwr", "HJgJtT4tvB", "Byg1v1HKDB", "r1eIiCNYwS"], "Byx_YAVYPH": ["Byx_YAVYPH", "S1lEX04tPr", "BJgMFxrYPB", "H1e0Wp4KvH", "rygf-kSYwH"], "ryeFY0EFwS": ["ryeFY0EFwS", "BJgnXpVYwS", "SJeLIgBKPS", "rklB76EKPr", "r1g87C4KwB"], "HJgCF0VFwr": ["HJgCF0VFwr", "BJlRs34Fvr", "HJem3yHKwH", "SkeFl1HKwr", "Bkxe2AVtPS"], "rJxlc0EtDr": ["rJxlc0EtDr", "rkxxA24FDr", "SyljQyBFDH", "SklKcRNYDH", "SJgwNerKvB"], "SyxV9ANFDH": ["SyxV9ANFDH", "HyeSin4FPB", "B1lGU64tDr", "r1ecqn4YwB", "H1ldzA4tPr"], "rklHqRVKvH": ["rklHqRVKvH", "r1xGP6VYwH", "BkxXe0Etwr", "S1xKd24twB", "S1xCPJHtDB"], "Bkxv90EKPB": ["Bkxv90EKPB", "rkeZIJBYvr", "BklEFpEYwS", "HkgB2TNYPS", "rklp93EtwH"], "H1e_cC4twS": ["H1e_cC4twS", "BkepbpNFwr", "ryxQuANKPB", "Hke0K1HKwr", "B1l4SgHKDH"], "SklKcRNYDH": ["SklKcRNYDH", "rkxxA24FDr", "Syx4wnEtvH", "B1eY_pVYvB", "Hklz71rYvS"], "HylpqA4FwS": ["HylpqA4FwS", "SJgmR0NKPr", "ryx1wRNFvB", "B1eY_pVYvB", "r1e9GCNKvH"], "Hkl1iRNFwS": ["Hkl1iRNFwS", "S1gSj0NKvB", "H1enKkrFDB", "HkgsPhNYPS", "r1g87C4KwB"], "Sklgs0NFvr": ["Sklgs0NFvr", "SJeNz04tDS", "SkxybANtDB", "HkxYzANYDB", "ryebG04YvB"], "ryxgsCVYPr": ["ryxgsCVYPr", "SJgVHkrYDH", "HygnDhEtvr", "SygWvAVFPr", "BJgQfkSYDS"], "SkgGjRVKDS": ["SkgGjRVKDS", "HJx8HANFDH", "ryghZJBKPS", "Sklf1yrYDr", "BJlS634tPr"], "rJeQoCNYDS": ["rJeQoCNYDS", "S1xitgHtvS", "rke7geHtwH", "HkgsWxrtPB", "H1ezFREtwH"], "S1gSj0NKvB": ["S1gSj0NKvB", "B1g8VkHFPH", "HyxjOyrKvr", "HkgxW0EYDS", "rJehVyrKwH"], "HklBjCEKvH": ["HklBjCEKvH", "Skep6TVYDB", "B1gX8kBtPr", "B1guLAVFDB", "rkgNKkHtvB"], "r1eIiCNYwS": ["r1eIiCNYwS", "ByeMPlHKPH", "SJgVHkrYDH", "ByxY8CNtvr", "ByxRM0Ntvr"], "S1l8oANFDH": ["S1l8oANFDH", "rJxX8T4Kvr", "H1ezFREtwH", "Sye57xStvB", "HklXn1BKDH"], "HklOo0VFDH": ["HklOo0VFDH", "rygGQyrFvH", "SJeYe0NtvH", "BygFVAEKDH", "HkxCzeHFDB"], "B1g5sA4twr": ["B1g5sA4twr", "ryeFY0EFwS", "SJgndT4KwB", "HyxnMyBKwB", "H1lj0nNFwB"], "HyxJhCEFDS": ["HyxJhCEFDS", "rklOg6EFwS", "H1xscnEKDr", "Hke0V1rKPS", "ByxtC2VtPB"], "Bkxe2AVtPS": ["Bkxe2AVtPS", "SJgVU0EKwS", "Hyx0slrFvH", "rkgO66VKDS", "H1lBj2VFPS"], "r1genAVKPB": ["r1genAVKPB", "Skln2A4YDB", "rJld3hEYvS", "rke-f6NKvS", "BkglSTNFDB"], "SJxZnR4YvB": ["SJxZnR4YvB", "Skep6TVYDB", "HJlxIJBFDr", "rye5YaEtPr", "B1guLAVFDB"], "r1xGnA4Kvr": ["r1xGnA4Kvr", "H1xscnEKDr", "SJgwzCEKwH", "rklOg6EFwS", "HyeaSkrYPH"], "B1xm3RVtwB": ["B1xm3RVtwB", "S1xKd24twB", "S1xCPJHtDB", "HJgEMpVFwB", "r1xGP6VYwH"], "HJeVnCEKwH": ["HJeVnCEKwH", "SJg7spEYDS", "HJeOekHKwr", "B1lPaCNtPB", "S1lxKlSKPH"], "HJxEhREKDH": ["HJxEhREKDH", "HygegyrYwH", "Skep6TVYDB", "BkgXHTNtvS", "B1guLAVFDB"], "Hklr204Fvr": ["Hklr204Fvr", "S1xtORNFwH", "B1lnbRNtwr", "BJgnXpVYwS", "r1ecqn4YwB"], "SJeD3CEFPH": ["SJeD3CEFPH", "S1evHerYPr", "BklEFpEYwS", "HkgB2TNYPS", "rklp93EtwH"], "SJgdnAVKDH": ["SJgdnAVKDH", "ByxT7TNFvH", "HJlWWJSFDH", "HJgExaVtwr", "SkxgnnNFvH"], "rkeu30EtvS": ["rkeu30EtvS", "SkgsACVKPH", "ByxdUySKvS", "HJx8HANFDH", "Bke89JBtvB"], "HJeqhA4YDS": ["HJeqhA4YDS", "HJlSmC4FPS", "SJeLIgBKPS", "ryeFY0EFwS", "B1esx6EYvr"], "B1lj20NFDS": ["B1lj20NFDS", "S1g6xeSKDS", "S1g7tpEYDS", "BkgnhTEtDS", "H1gfFaEYDS"], "ryxjnREFwH": ["ryxjnREFwH", "SygWvAVFPr", "HJgJtT4tvB", "BJlzm64tDH", "SJgVHkrYDH"], "Skln2A4YDB": ["Skln2A4YDB", "r1genAVKPB", "rJeINp4KwH", "rJld3hEYvS", "SylOlp4FvH"], "Hkx6hANtwH": ["Hkx6hANtwH", "SJeqs6EFvB", "rylHspEKPr", "r1lGO0EKDH", "SJetQpEYvB"], "B1lPaCNtPB": ["B1lPaCNtPB", "HJeOekHKwr", "S1lxKlSKPH", "Hye1RJHKwB", "H1x5wRVtvS"], "H1guaREYPr": ["H1guaREYPr", "BJgza6VtPB", "B1l8L6EtDS", "r1gfQgSFDr", "H1x5wRVtvS"], "S1lOTC4tDS": ["S1lOTC4tDS", "HJgLZR4KvH", "SJg5J6NtDr", "H1ezFREtwH", "rylvYaNYDH"], "BJxt60VtPr": ["BJxt60VtPr", "rkl03ySYDH", "SkeyppEFvS", "Hyg9anEFPS", "BkxfaTVFwH"], "r1gRTCVFvB": ["r1gRTCVFvB", "H1eA7AEtvS", "rJeqeCEtvH", "B1e3OlStPB", "B1gZV1HYvS"], "HJgC60EtwB": ["HJgC60EtwB", "rke7geHtwH", "S1xKd24twB", "SylOlp4FvH", "HJgEMpVFwB"], "S1l-C0NtwS": ["S1l-C0NtwS", "HJeT3yrtDr", "HyeYTgrFPB", "r1xCMyBtPS", "SJxE8erKDH"], "SJgmR0NKPr": ["SJgmR0NKPr", "HylpqA4FwS", "ryx1wRNFvB", "r1e9GCNKvH", "BJx040EFvH"], "HklUCCVKDB": ["HklUCCVKDB", "BkglSTNFDB", "rklnDgHtDS", "SJxIm0VtwH", "HJxNAnVtDS"], "rkgt0REKwS": ["rkgt0REKwS", "Byg9A24tvB", "HyxY6JHKwr", "ryxOUTVYDH", "r1e_FpNFDr"], "SkgsACVKPH": ["SkgsACVKPH", "ByxdUySKvS", "Bke89JBtvB", "ryl3ygHYDB", "HJeTo2VFwH"], "SJgaRA4FPH": ["SJgaRA4FPH", "rJgqMRVYvr", "SJx0q1rtvS", "HJezF3VYPB", "Byg-wJSYDS"], "HJlA0C4tPS": ["HJlA0C4tPS", "HJe_Z04Yvr", "SkgpBJrtvS", "ryxyCeHtPB", "Syx79eBKwr"], "rJeW1yHYwH": ["rJeW1yHYwH", "SJxzFySKwH", "r1evOhEKvH", "r1lGO0EKDH", "BJxWx0NYPr"], "Sklf1yrYDr": ["Sklf1yrYDr", "BygSP6Vtvr", "ryxOUTVYDH", "HJx8HANFDH", "ryghZJBKPS"], "ByxGkySKwH": ["ByxGkySKwH", "SyxIWpVYvr", "BJxVI04YvB", "ByeNra4FDB", "BJl6bANtwH"], "HJx81ySKwr": ["HJx81ySKwr", "HkgeGeBYDB", "HkgH0TEYwH", "S1g7tpEYDS", "BygXFkSYDH"], "Skxuk1rFwB": ["Skxuk1rFwB", "SJxSDxrKDr", "Hke0V1rKPS", "BJx040EFvH", "rJx1Na4Fwr"], "B1gskyStwr": ["B1gskyStwr", "HkxjqxBYDB", "Skln2A4YDB", "SkeAaJrKDS", "rklHqRVKvH"], "Ske31kBtPr": ["Ske31kBtPr", "rygeHgSFDH", "H1laeJrKDB", "S1g6xeSKDS", "BJxG_0EtDS"], "Bke61krFvS": ["Bke61krFvS", "ByeUBANtvB", "H1lj0nNFwB", "BJxkOlSYDH", "BygPO2VKPH"], "HygegyrYwH": ["HygegyrYwH", "HJlxIJBFDr", "SJxIm0VtwH", "B1guLAVFDB", "BkglSTNFDB"], "r1gelyrtwH": ["r1gelyrtwH", "ryxmb1rKDS", "BJeKwTNFvB", "HyeSin4FPB", "B1lGU64tDr"], "r1lZgyBYwS": ["r1lZgyBYwS", "HyxjOyrKvr", "HkgxW0EYDS", "rJehVyrKwH", "H1gmHaEKwB"], "BJeGlJStPr": ["BJeGlJStPr", "rJld3hEYvS", "BJgZGeHFPH", "Bkl7bREtDr", "HkxjqxBYDB"], "r1eBeyHFDH": ["r1eBeyHFDH", "rklr9kHFDB", "ByxaUgrFvH", "S1ldO2EFPr", "Syx79eBKwr"], "BJewlyStDr": ["BJewlyStDr", "Sye57xStvB", "BJgy96EYvr", "S1xCPJHtDB", "r1xGP6VYwH"], "r1lOgyrKDS": ["r1lOgyrKDS", "rklEj2EFvB", "rJxe3xSYDS", "ryxz8CVYDH", "Syx1DkSYwB"], "HJeOekHKwr": ["HJeOekHKwr", "B1lPaCNtPB", "Bke_DertPB", "S1lxKlSKPH", "HJeVnCEKwH"], "rJxtgJBKDr": ["rJxtgJBKDr", "ryxyCeHtPB", "BylVcTNtDS", "ryebG04YvB", "HkxQRTNYPH"], "SkeFl1HKwr": ["SkeFl1HKwr", "HJgCF0VFwr", "B1x6BTEKwr", "rkgOlCVYvB", "BJlRs34Fvr"], "S1ltg1rFDS": ["S1ltg1rFDS", "rke7geHtwH", "S1glGANtDr", "rkgU1gHtvr", "HkxlcnVFwB"], "rkecl1rtwB": ["rkecl1rtwB", "Hkx1qkrKPr", "r1laNeBYPB", "B1e3OlStPB", "SkgGjRVKDS"], "rygixkHKDH": ["rygixkHKDH", "Byg5ZANtvH", "S1gEIerYwH", "SJeY-1BKDS", "rkg1ngrFPr"], "rJlnxkSYPS": ["rJlnxkSYPS", "Hyx-jyBFPr", "HJgExaVtwr", "BygSP6Vtvr", "rJlnOhVYPS"], "Hke3gyHYwH": ["Hke3gyHYwH", "rkgg6xBYDH", "HkgsPhNYPS", "SkxxtgHKPS", "r1e_FpNFDr"], "SkxpxJBKwS": ["SkxpxJBKwS", "S1lEX04tPr", "rJxGLlBtwH", "SJxbHkrKDH", "rkg-TJBFPB"], "H1laeJrKDB": ["H1laeJrKDB", "HylsTT4FvB", "r1gfQgSFDr", "SJxDDpEKvH", "S1g6xeSKDS"], "HJxyZkBKDr": ["HJxyZkBKDr", "H1loF2NFwr", "SJx9ngStPH", "BJxH22EKPS", "HygrdpVKvr"], "HJlWWJSFDH": ["HJlWWJSFDH", "BJgQ4lSFPH", "SkxgnnNFvH", "BylVcTNtDS", "rkg-mA4FDr"], "rygf-kSYwH": ["rygf-kSYwH", "r1etN1rtPB", "SJlpYJBKvH", "rylVHR4FPB", "S1xitgHtvS"], "BygzbyHFvB": ["BygzbyHFvB", "ByxtC2VtPB", "rklOg6EFwS", "H1lZJpVFvr", "H1xscnEKDr"], "ryxmb1rKDS": ["ryxmb1rKDS", "HJenn6VFvB", "HyeSin4FPB", "BkgYPREtPr", "BJeKwTNFvB"], "SJeY-1BKDS": ["SJeY-1BKDS", "HJlxIJBFDr", "BkglSTNFDB", "SJxIm0VtwH", "HygegyrYwH"], "ryghZJBKPS": ["ryghZJBKPS", "HJx8HANFDH", "Sklf1yrYDr", "SkgGjRVKDS", "Syx4wnEtvH"], "Hygab1rKDS": ["Hygab1rKDS", "rygfnn4twS", "H1gBhkBFDH", "S1xtORNFwH", "rkeu30EtvS"], "B1lJzyStvS": ["B1lJzyStvS", "S1e_9xrFvS", "SyljQyBFDH", "Hyx-jyBFPr", "HJx81ySKwr"], "HyeJf1HKvS": ["HyeJf1HKvS", "S1e2agrFvS", "r1lGO0EKDH", "rkeuAhVKvB", "B1lnbRNtwr"], "rkllGyBFPH": ["rkllGyBFPH", "rkl8sJBYvH", "SJgndT4KwB", "rkgfdeBYvH", "HyxyIgHFvr"], "SJlbGJrtDB": ["SJlbGJrtDB", "HJeTo2VFwH", "SJem8lSFwB", "r1e9GCNKvH", "ryl3ygHYDB"], "rJgzzJHtDB": ["rJgzzJHtDB", "HyxJhCEFDS", "Hke0V1rKPS", "SJgwzCEKwH", "H1xscnEKDr"], "BJgQfkSYDS": ["BJgQfkSYDS", "rJld3hEYvS", "BJgnXpVYwS", "ryxdEkHtPS", "rJeINp4KwH"], "ByedzkrKvH": ["ByedzkrKvH", "rJx4p3NYDB", "S1xCPJHtDB", "BJewlyStDr", "Bkl5kxrKDr"], "S1esMkHYPr": ["S1esMkHYPr", "r1laNeBYPB", "BJxg_hVtwH", "B1lnbRNtwr", "r1lGO0EKDH"], "HyxnMyBKwB": ["HyxnMyBKwB", "rklHqRVKvH", "r1genAVKPB", "BkxXe0Etwr", "SJezGp4YPr"], "r1xCMyBtPS": ["r1xCMyBtPS", "Hyl7ygStwB", "rylXBkrYDS", "BJgQ4lSFPH", "S1l-C0NtwS"], "rygGQyrFvH": ["rygGQyrFvH", "SJeYe0NtvH", "HklOo0VFDH", "B1l8L6EtDS", "BJgza6VtPB"], "Hklz71rYvS": ["Hklz71rYvS", "SJxIm0VtwH", "ryxz8CVYDH", "HJxNAnVtDS", "BJgnXpVYwS"], "HkxdQkSYDB": ["HkxdQkSYDB", "S1lEX04tPr", "B1gZV1HYvS", "BJxWx0NYPr", "r1lfF2NYvH"], "SyljQyBFDH": ["SyljQyBFDH", "rkxxA24FDr", "rJxlc0EtDr", "SklKcRNYDH", "S1e_9xrFvS"], "rkl3m1BFDB": ["rkl3m1BFDB", "SJgzLkBKPB", "S1xCPJHtDB", "HJl8_eHYvS", "S1xitgHtvS"], "rklTmyBKPH": ["rklTmyBKPH", "HylxE1HKwS", "BylQSxHFwr", "r1eowANFvr", "SkgsACVKPH"], "BJl07ySKvS": ["BJl07ySKvS", "BkxUvnEYDH", "HJlfuTEtvB", "SygWvAVFPr", "B1eB5xSFvr"], "Sye0XkBKvS": ["Sye0XkBKvS", "SJxIm0VtwH", "HJxNAnVtDS", "rygjmpVFvB", "BkglSTNFDB"], "H1lxVyStPH": ["H1lxVyStPH", "BJxkOlSYDH", "H1loF2NFwr", "rJehNT4YPr", "r1e_FpNFDr"], "HylxE1HKwS": ["HylxE1HKwS", "rklTmyBKPH", "SkgsACVKPH", "BJlS634tPr", "BkeWw6VFwr"], "B1gZV1HYvS": ["B1gZV1HYvS", "S1lEX04tPr", "HJgEMpVFwB", "S1l8oANFDH", "BJl-5pNKDB"], "BJgWE1SFwS": ["BJgWE1SFwS", "SylkYeHtwr", "BJxG_0EtDS", "S1efxTVYDr", "BJliakStvH"], "Byx4NkrtDS": ["Byx4NkrtDS", "ByexElSYDr", "HJlWWJSFDH", "BJgQ4lSFPH", "Bkg0u3Etwr"], "BJgr4kSFDS": ["BJgr4kSFDS", "SygW0TEFwH", "Skep6TVYDB", "B1guLAVFDB", "HygegyrYwH"], "B1g8VkHFPH": ["B1g8VkHFPH", "S1gSj0NKvB", "Hyl7ygStwB", "Bkxe2AVtPS", "Bke89JBtvB"], "H1gDNyrKDS": ["H1gDNyrKDS", "ryxGuJrFvS", "BJxH22EKPS", "BJeB5hVtvB", "BkxSmlBFvr"], "H1edEyBKDS": ["H1edEyBKDS", "HklBjCEKvH", "SJem8lSFwB", "rylXBkrYDS", "ByxdUySKvS"], "ryxdEkHtPS": ["ryxdEkHtPS", "BJgnXpVYwS", "r1etN1rtPB", "BJgQfkSYDS", "Skln2A4YDB"], "r1etN1rtPB": ["r1etN1rtPB", "ryxdEkHtPS", "SylOlp4FvH", "rJeINp4KwH", "rJld3hEYvS"], "rkgqN1SYvr": ["rkgqN1SYvr", "rkg1ngrFPr", "H1lj0nNFwB", "SJgndT4KwB", "HJxEhREKDH"], "HyxjNyrtPr": ["HyxjNyrtPr", "B1lPaCNtPB", "H1x5wRVtvS", "S1lxKlSKPH", "HJeOekHKwr"], "rJehVyrKwH": ["rJehVyrKwH", "BkgXT24tDS", "ryxK0JBtPr", "H1lBj2VFPS", "rkgO66VKDS"], "SyxhVkrYvr": ["SyxhVkrYvr", "Skxuk1rFwB", "SyxIWpVYvr", "H1gfFaEYDS", "SylO2yStDr"], "Hke0V1rKPS": ["Hke0V1rKPS", "H1lZJpVFvr", "rklOg6EFwS", "H1xscnEKDr", "HyxJhCEFDS"], "SJexHkSFPS": ["SJexHkSFPS", "BkxXe0Etwr", "rke7geHtwH", "H1exf64KwH", "SylOlp4FvH"], "SJxbHkrKDH": ["SJxbHkrKDH", "SkxpxJBKwS", "B1gZV1HYvS", "S1lEX04tPr", "rJxGLlBtwH"], "r1xMH1BtvB": ["r1xMH1BtvB", "BJgQ4lSFPH", "HJlWWJSFDH", "Hyl7ygStwB", "SkxgnnNFvH"], "SklGryBtwr": ["SklGryBtwr", "rylvYaNYDH", "Byx4NkrtDS", "rJl31TNYPr", "HklSeREtPB"], "ByxQB1BKwH": ["ByxQB1BKwH", "r1eIiCNYwS", "B1gF56VYPH", "BJlS634tPr", "S1xtORNFwH"], "rylXBkrYDS": ["rylXBkrYDS", "SJl5Np4tPr", "H1emfT4twB", "HkgB2TNYPS", "SJx9ngStPH"], "SJgVHkrYDH": ["SJgVHkrYDH", "r1eIiCNYwS", "SJxstlHFPH", "SygWvAVFPr", "rkeuAhVKvB"], "BJlBSkHtDS": ["BJlBSkHtDS", "r1x0lxrFPS", "rkgfdeBYvH", "B1x6BTEKwr", "Skgvy64tvr"], "SJlKrkSFPH": ["SJlKrkSFPH", "BkeWw6VFwr", "H1xscnEKDr", "HkgTTh4FDH", "Sye_OgHFwH"], "SkgpBJrtvS": ["SkgpBJrtvS", "ryxyCeHtPB", "HJlA0C4tPS", "BJgqQ6NYvB", "BygSP6Vtvr"], "HyeaSkrYPH": ["HyeaSkrYPH", "H1xscnEKDr", "HJxdTxHYvB", "SJlHwkBYDH", "SyevYxHtDB"], "BJeAHkrYDS": ["BJeAHkrYDS", "S1l8oANFDH", "rkg-TJBFPB", "S1xKd24twB", "S1xCPJHtDB"], "HJlxIJBFDr": ["HJlxIJBFDr", "HygegyrYwH", "SJxIm0VtwH", "BkglSTNFDB", "B1guLAVFDB"], "r1egIyBFPS": ["r1egIyBFPS", "S1eZYeHFDS", "HJgLZR4KvH", "SkeuexBtDr", "SylL0krYPS"], "rkeZIJBYvr": ["rkeZIJBYvr", "BklEFpEYwS", "rklp93EtwH", "HkgB2TNYPS", "rkgAGAVKPr"], "SJgzLkBKPB": ["SJgzLkBKPB", "rkl3m1BFDB", "S1xCPJHtDB", "B1x6w0EtwH", "ryg48p4tPH"], "B1gX8kBtPr": ["B1gX8kBtPr", "Skep6TVYDB", "B1guLAVFDB", "rklk_ySYPB", "BJgr4kSFDS"], "BJxSI1SKDH": ["BJxSI1SKDH", "HkxQRTNYPH", "B1elCp4KwH", "Byl8hhNYPS", "SylkYeHtwr"], "rkeIIkHKvS": ["rkeIIkHKvS", "r1laNeBYPB", "Bkeeca4Kvr", "rJg76kStwH", "r1lGO0EKDH"], "HJgLLyrYwB": ["HJgLLyrYwB", "rylrdxHFDr", "S1xKd24twB", "BJliakStvH", "Skl4mRNYDr"], "HyevIJStwH": ["HyevIJStwH", "HJgCF0VFwr", "rkgg6xBYDH", "Hke3gyHYwH", "SkgscaNYPS"], "ByxdUySKvS": ["ByxdUySKvS", "SkgsACVKPH", "Bke89JBtvB", "rkeu30EtvS", "S1lxKlSKPH"], "BJgd81SYwr": ["BJgd81SYwr", "rkgAGAVKPr", "rkeZIJBYvr", "HkgB2TNYPS", "BklEFpEYwS"], "HkgsUJrtDB": ["HkgsUJrtDB", "B1gdkxHFDH", "Hkekl0NFPr", "B1x62TNtDS", "S1eRbANtDB"], "SJlRUkrFPS": ["SJlRUkrFPS", "ryxGuJrFvS", "H1lmhaVtvr", "ryeYpJSKwr", "BJeB5hVtvB"], "S1eALyrYDH": ["S1eALyrYDH", "HJeO7RNKPr", "rkgvXlrKwH", "HygnDhEtvr", "HJlfuTEtvB"], "SklkDkSFPB": ["SklkDkSFPB", "ByxdUySKvS", "Bke89JBtvB", "SkgsACVKPH", "BylQSxHFwr"], "Syx1DkSYwB": ["Syx1DkSYwB", "Hklz71rYvS", "ryeFY0EFwS", "BJgnXpVYwS", "SJeLIgBKPS"], "Byg1v1HKDB": ["Byg1v1HKDB", "ryxjnREFwH", "HJgJtT4tvB", "SJlh8CEYDB", "SJgVHkrYDH"], "Byg-wJSYDS": ["Byg-wJSYDS", "HkgsPhNYPS", "SJgaRA4FPH", "S1g8K1BFwS", "BJeB5hVtvB"], "HJgSwyBKvr": ["HJgSwyBKvr", "SygagpEKwB", "HJgK0h4Ywr", "Hyl9xxHYPr", "SyxL2TNtvr"], "SJlHwkBYDH": ["SJlHwkBYDH", "SJxhNTNYwB", "H1xscnEKDr", "rJxAo2VYwr", "HJxdTxHYvB"], "SJgIPJBFvH": ["SJgIPJBFvH", "rkgg6xBYDH", "r1e_FpNFDr", "SkxxtgHKPS", "HJe_yR4Fwr"], "BJxwPJHFwS": ["BJxwPJHFwS", "ByxRM0Ntvr", "Skxuk1rFwB", "ByeMPlHKPH", "SJlKrkSFPH"], "HJgcvJBFvB": ["HJgcvJBFvB", "SylL0krYPS", "S1xKd24twB", "rJxX8T4Kvr", "H1ezFREtwH"], "rke2P1BFwS": ["rke2P1BFwS", "rJeW1yHYwH", "BylA_C4tPr", "BkgnhTEtDS", "ByxxgCEYDS"], "HkxTwkrKDB": ["HkxTwkrKDB", "r1g6ogrtDr", "ByxRM0Ntvr", "BJgNJgSFPS", "SylVNerFvr"], "S1xCPJHtDB": ["S1xCPJHtDB", "BJewlyStDr", "HJl8_eHYvS", "rklHqRVKvH", "rkl3m1BFDB"], "rklk_ySYPB": ["rklk_ySYPB", "B1gX8kBtPr", "SygW0TEFwH", "BkeWw6VFwr", "B1guLAVFDB"], "B1eyO1BFPr": ["B1eyO1BFPr", "r1gixp4FPH", "rkeNfp4tPr", "HJxNAnVtDS", "SJxIm0VtwH"], "B1eWOJHKvB": ["B1eWOJHKvB", "Byg9A24tvB", "HyxY6JHKwr", "rkgOlCVYvB", "rkgt0REKwS"], "ryxGuJrFvS": ["ryxGuJrFvS", "H1gDNyrKDS", "Hke3gyHYwH", "SJeLIgBKPS", "rkllGyBFPH"], "Hkx7_1rKwS": ["Hkx7_1rKwS", "SJlVY04FwH", "BJgnXpVYwS", "BJgQfkSYDS", "rkeNfp4tPr"], "SJxSOJStPr": ["SJxSOJStPr", "rklnDgHtDS", "Hklso24Kwr", "HklUCCVKDB", "r1gdj2EKPB"], "ryeHuJBtPH": ["ryeHuJBtPH", "rkeIIkHKvS", "r1laNeBYPB", "rJg76kStwH", "r1lGO0EKDH"], "HyxjOyrKvr": ["HyxjOyrKvr", "HkgxW0EYDS", "r1lZgyBYwS", "H1gmHaEKwB", "rJehVyrKwH"], "rkgbYyHtwB": ["rkgbYyHtwB", "S1xKd24twB", "rke-f6NKvS", "rylrdxHFDr", "HJgEMpVFwB"], "SJxzFySKwH": ["SJxzFySKwH", "rJeW1yHYwH", "r1evOhEKvH", "r1laNeBYPB", "r1lGO0EKDH"], "BJlQtJSKDB": ["BJlQtJSKDB", "SkeAaJrKDS", "BJewlyStDr", "r1lOgyrKDS", "ByedzkrKvH"], "BygXFkSYDH": ["BygXFkSYDH", "HJgSwyBKvr", "S1g6xeSKDS", "H1gfFaEYDS", "SygagpEKwB"], "rkgNKkHtvB": ["rkgNKkHtvB", "Skep6TVYDB", "SygW0TEFwH", "HJxEhREKDH", "rklk_ySYPB"], "S1g8K1BFwS": ["S1g8K1BFwS", "BJeB5hVtvB", "BylA_C4tPr", "r1lGO0EKDH", "Byg-wJSYDS"], "BylsKkHYvH": ["BylsKkHYvH", "Syx1DkSYwB", "rylBK34FDS", "HJx8HANFDH", "SyxIWpVYvr"], "H1enKkrFDB": ["H1enKkrFDB", "SkxxtgHKPS", "rJg8TeSFDH", "r1e_FpNFDr", "Skxuk1rFwB"], "SJlpYJBKvH": ["SJlpYJBKvH", "rygf-kSYwH", "S1xitgHtvS", "H1eCw3EKvH", "HJeiDpVFPr"], "Hke0K1HKwr": ["Hke0K1HKwr", "rJeIcTNtvS", "SJxstlHFPH", "H1e_cC4twS", "Hkl1iRNFwS"], "Hkx1qkrKPr": ["Hkx1qkrKPr", "rkecl1rtwB", "SkgsACVKPH", "S1ldO2EFPr", "BJg4NgBKvH"], "BJe-91BtvH": ["BJe-91BtvH", "B1e3OlStPB", "B1x1ma4tDr", "HJgExaVtwr", "rJeqeCEtvH"], "BJlZ5ySKPH": ["BJlZ5ySKPH", "Hyg96gBKPS", "SJl5Np4tPr", "BJe-91BtvH", "B1gF56VYPH"], "rkem91rtDB": ["rkem91rtDB", "r1lGO0EKDH", "BJxg_hVtwH", "rkeIIkHKvS", "r1lfF2NYvH"], "rklr9kHFDB": ["rklr9kHFDB", "HklSeREtPB", "Skey4eBYPS", "H1gB4RVKvB", "BJgNJgSFPS"], "Bke89JBtvB": ["Bke89JBtvB", "SkgsACVKPH", "ByxdUySKvS", "rJehVyrKwH", "rkeu30EtvS"], "B1xwcyHFDr": ["B1xwcyHFDr", "Syx79eBKwr", "Hyg9anEFPS", "rkgpv2VFvr", "HkgsPhNYPS"], "SklD9yrFPS": ["SklD9yrFPS", "SkgsACVKPH", "rJeqeCEtvH", "HylxE1HKwS", "rklTmyBKPH"], "SJeq9JBFvH": ["SJeq9JBFvH", "BkeoaeHKDS", "HkgH0TEYwH", "Byg9A24tvB", "HJg2b0VYDr"], "SJx0q1rtvS": ["SJx0q1rtvS", "SJeQEp4YDH", "HkgH0TEYwH", "H1xscnEKDr", "BkgzMCVtPB"], "Hyx-jyBFPr": ["Hyx-jyBFPr", "ByxdUySKvS", "Bke89JBtvB", "ryxOUTVYDH", "rygFWAEFwS"], "S1e4jkSKvB": ["S1e4jkSKvB", "S1gSj0NKvB", "SJgIPJBFvH", "HyevIJStwH", "r1e_FpNFDr"], "B1gHokBKwS": ["B1gHokBKwS", "BJgZGeHFPH", "rklbKA4YDS", "BJxG_0EtDS", "H1exf64KwH"], "rkl8sJBYvH": ["rkl8sJBYvH", "rkllGyBFPH", "SkgscaNYPS", "SJgndT4KwB", "H1enKkrFDB"], "B1lDoJSYDH": ["B1lDoJSYDH", "H1eqQeHFDS", "rkeu30EtvS", "H1gDNyrKDS", "rygjHxrYDB"], "rkxDoJBYPB": ["rkxDoJBYPB", "BylA_C4tPr", "r1laNeBYPB", "BJe8pkHFwS", "r1lGO0EKDH"], "BkevoJSYPB": ["BkevoJSYPB", "rJgBd2NYPH", "r1lL4a4tDB", "S1eALyrYDH", "B1eWOJHKvB"], "SylKikSYDH": ["SylKikSYDH", "ByeMPlHKPH", "r1eIiCNYwS", "rkgNKkHtvB", "SJe5P6EYvS"], "rJgsskrFwH": ["rJgsskrFwH", "SJgMK64Ywr", "HJgzt2VKPB", "rJgUfTEYvH", "SJeLopEYDH"], "S1g2skStPB": ["S1g2skStPB", "rklbKA4YDS", "S1xKd24twB", "HJli2hNKDH", "rke3TJrtPS"], "rJe2syrtvS": ["rJe2syrtvS", "rke7geHtwH", "rke-f6NKvS", "S1lOTC4tDS", "HkxjqxBYDB"], "rkg6sJHYDr": ["rkg6sJHYDr", "HJgLZR4KvH", "H1e0Wp4KvH", "SkxpxJBKwS", "H1lmhaVtvr"], "HylAoJSKvH": ["HylAoJSKvH", "rye5YaEtPr", "rkeNfp4tPr", "SJxIm0VtwH", "Byg5ZANtvH"], "S1xWh1rYwB": ["S1xWh1rYwB", "SkeFl1HKwr", "Hye1kTVFDS", "rJxtgJBKDr", "B1esx6EYvr"], "SylzhkBtDB": ["SylzhkBtDB", "rkgpv2VFvr", "Hyl7ygStwB", "BylVcTNtDS", "ryxyCeHtPB"], "HklXn1BKDH": ["HklXn1BKDH", "S1l8oANFDH", "rJxX8T4Kvr", "Sye57xStvB", "BJgMFxrYPB"], "HJem3yHKwH": ["HJem3yHKwH", "H1xscnEKDr", "Hke0V1rKPS", "SyevYxHtDB", "HyxJhCEFDS"], "rkxNh1Stvr": ["rkxNh1Stvr", "BJlahxHYDS", "HygpthEtvr", "rJgUfTEYvH", "HklBjCEKvH"], "H1gBhkBFDH": ["H1gBhkBFDH", "r1g6ogrtDr", "Hygab1rKDS", "BJgNJgSFPS", "B1e3OlStPB"], "Skx82ySYPH": ["Skx82ySYPH", "ByxT7TNFvH", "B1eY_pVYvB", "S1xtORNFwH", "rJgBd2NYPH"], "SylO2yStDr": ["SylO2yStDr", "SJlbGJrtDB", "Syx4wnEtvH", "SkgsACVKPH", "HJeTo2VFwH"], "HJeT3yrtDr": ["HJeT3yrtDr", "S1l-C0NtwS", "H1eA7AEtvS", "SklD9yrFPS", "SJleNCNtDH"], "rkl03ySYDH": ["rkl03ySYDH", "BkxfaTVFwH", "SJxrKgStDH", "SklD9yrFPS", "BJgMFxrYPB"], "rkg-TJBFPB": ["rkg-TJBFPB", "BJgy96EYvr", "Sye57xStvB", "S1xKd24twB", "SJleNCNtDH"], "SkxQp1StDH": ["SkxQp1StDH", "r1lGO0EKDH", "BylA_C4tPr", "S1e2agrFvS", "BJe8pkHFwS"], "rJg76kStwH": ["rJg76kStwH", "rkeIIkHKvS", "r1laNeBYPB", "Bkeeca4Kvr", "r1lZ7AEKvB"], "BJe8pkHFwS": ["BJe8pkHFwS", "BylA_C4tPr", "r1lGO0EKDH", "S1ldO2EFPr", "S1e2agrFvS"], "ryeYpJSKwr": ["ryeYpJSKwr", "rke7geHtwH", "ryxz8CVYDH", "rygf-kSYwH", "ryxyCeHtPB"], "HyxY6JHKwr": ["HyxY6JHKwr", "rkgt0REKwS", "HkgsPhNYPS", "rkgOlCVYvB", "Bkxe2AVtPS"], "BJliakStvH": ["BJliakStvH", "S1xKd24twB", "HJgLLyrYwB", "rkg-TJBFPB", "HJli2hNKDH"], "rke3TJrtPS": ["rke3TJrtPS", "rJeINp4KwH", "SylOlp4FvH", "BJliakStvH", "r1etN1rtPB"], "ryxC6kSYPr": ["ryxC6kSYPr", "B1eB5xSFvr", "Skln2A4YDB", "SJg7KhVKPH", "Hklz71rYvS"], "SkeAaJrKDS": ["SkeAaJrKDS", "Bkg0u3Etwr", "r1xGP6VYwH", "rklHqRVKvH", "BJlQtJSKDB"], "Hye1RJHKwB": ["Hye1RJHKwB", "B1lPaCNtPB", "HJeOekHKwr", "H1x5wRVtvS", "S1lxKlSKPH"], "SkgGCkrKvH": ["SkgGCkrKvH", "HyxjOyrKvr", "HyxG3p4twS", "B1lLw6EYwB", "r1lZgyBYwS"], "SylL0krYPS": ["SylL0krYPS", "H1xscnEKDr", "SJlHwkBYDH", "HJgEMpVFwB", "Sye_OgHFwH"], "H1l_0JBYwS": ["H1l_0JBYwS", "r1lGO0EKDH", "Hke3gyHYwH", "HkgaETNtDB", "S1lxKlSKPH"], "ryxK0JBtPr": ["ryxK0JBtPr", "Hyx0slrFvH", "BkgXT24tDS", "H1lBj2VFPS", "rJehVyrKwH"], "rkxs0yHFPH": ["rkxs0yHFPH", "B1xSperKvH", "ByeUBANtvB", "HklSeREtPB", "H1ebhnEYDH"], "HJlnC1rKPB": ["HJlnC1rKPB", "ByxRM0Ntvr", "B1esx6EYvr", "BJg1f6EFDB", "HJe6uANtwH"], "BkxRRkSKwr": ["BkxRRkSKwr", "rJlUt0EYwS", "HJxK5pEYvr", "B1lGU64tDr", "BJxwPJHFwS"], "HkxARkrFwB": ["HkxARkrFwB", "SygpC6Ntvr", "Hke-WTVtwr", "SkxQp1StDH", "rJljdh4KDH"], "HyxJ1xBYDH": ["HyxJ1xBYDH", "Skep6TVYDB", "B1gX8kBtPr", "B1guLAVFDB", "SJxZnR4YvB"], "B1e-kxSKDH": ["B1e-kxSKDH", "SkeyppEFvS", "BJeKwTNFvB", "HyeSin4FPB", "HJgLZR4KvH"], "rJxbJeHFPS": ["rJxbJeHFPS", "rJg76kStwH", "r1laNeBYPB", "rkeuAhVKvB", "HJgJtT4tvB"], "Hyl7ygStwB": ["Hyl7ygStwB", "H1eA7AEtvS", "BJlzm64tDH", "BJgQ4lSFPH", "SkeHuCVFDr"], "BJgNJgSFPS": ["BJgNJgSFPS", "HJe6uANtwH", "r1g6ogrtDr", "HkxTwkrKDB", "SylVNerFvr"], "HkeryxBtPB": ["HkeryxBtPB", "HkgTTh4FDH", "HJxdTxHYvB", "rklOg6EFwS", "H1lZJpVFvr"], "rkgU1gHtvr": ["rkgU1gHtvr", "HkxlcnVFwB", "S1glGANtDr", "rJld3hEYvS", "rJeINp4KwH"], "rylwJxrYDS": ["rylwJxrYDS", "Hyl7ygStwB", "HJlfuTEtvB", "HJlWWJSFDH", "BJgQ4lSFPH"], "BygdyxHFDS": ["BygdyxHFDS", "S1evHerYPr", "rkgMkCEtPB", "SJeD3CEFPH", "S1xKd24twB"], "B1gdkxHFDH": ["B1gdkxHFDH", "HkgsUJrtDB", "Hkekl0NFPr", "H1ebhnEYDH", "SygagpEKwB"], "SygKyeHKDH": ["SygKyeHKDH", "S1xKd24twB", "SJg5J6NtDr", "BJewlyStDr", "BJgy96EYvr"], "Bkl5kxrKDr": ["Bkl5kxrKDr", "Syg-ET4FPS", "S1xCPJHtDB", "ByedzkrKvH", "B1xMEerYvB"], "Hkl9JlBYvr": ["Hkl9JlBYvr", "SJeD3CEFPH", "rJeINp4KwH", "rJld3hEYvS", "S1evHerYPr"], "ryl3ygHYDB": ["ryl3ygHYDB", "HJeTo2VFwH", "SkgsACVKPH", "r1e9GCNKvH", "BJxkOlSYDH"], "rJxWxxSYvB": ["rJxWxxSYvB", "ByeUBANtvB", "HklQYxBKwS", "rkg1ngrFPr", "r1e_FpNFDr"], "Hkg-xgrYvH": ["Hkg-xgrYvH", "SklOUpEYvB", "rylXBkrYDS", "BklEFpEYwS", "HkgB2TNYPS"], "rke7geHtwH": ["rke7geHtwH", "SylOlp4FvH", "S1xKd24twB", "HJgC60EtwB", "SJeD3CEFPH"], "r1lPleBFvH": ["r1lPleBFvH", "SJeQEp4YDH", "SyxIWpVYvr", "r1xGnA4Kvr", "Hke0V1rKPS"], "SkeuexBtDr": ["SkeuexBtDr", "SygagpEKwB", "HJgSwyBKvr", "HkgsPhNYPS", "rJleKgrKwS"], "Hyl9xxHYPr": ["Hyl9xxHYPr", "HJgK0h4Ywr", "HJgSwyBKvr", "SygagpEKwB", "SJxpsxrYPS"], "S1g6xeSKDS": ["S1g6xeSKDS", "S1g7tpEYDS", "BJxG_0EtDS", "H1laeJrKDB", "SklOUpEYvB"], "r1x0lxrFPS": ["r1x0lxrFPS", "BJlBSkHtDS", "BJg4NgBKvH", "rkgO66VKDS", "Hyx0slrFvH"], "HklxbgBKvr": ["HklxbgBKvr", "S1e_9xrFvS", "r1etN1rtPB", "SJxUjlBtwB", "Skln2A4YDB"], "B1eWbxStPH": ["B1eWbxStPH", "B1lnbRNtwr", "rkeuAhVKvB", "HyeJf1HKvS", "r1laNeBYPB"], "Hkem-lrtvH": ["Hkem-lrtvH", "SJxhNTNYwB", "SJlHwkBYDH", "SklTQCNtvS", "H1xscnEKDr"], "H1xFWgrFPS": ["H1xFWgrFPS", "Hkem-lrtvH", "rJxAo2VYwr", "Hke0V1rKPS", "r1lF_CEYwS"], "HkgsWxrtPB": ["HkgsWxrtPB", "SJeD3CEFPH", "BklEFpEYwS", "S1evHerYPr", "rkeZIJBYvr"], "ryx6WgStPB": ["ryx6WgStPB", "BygSP6Vtvr", "Sklf1yrYDr", "BJlahxHYDS", "BJxI5gHKDr"], "HkgeGeBYDB": ["HkgeGeBYDB", "HJx81ySKwr", "SJx0q1rtvS", "S1g6xeSKDS", "S1g7tpEYDS"], "BJgZGeHFPH": ["BJgZGeHFPH", "rke7geHtwH", "S1xKd24twB", "rJld3hEYvS", "S1xitgHtvS"], "ByeGzlrKwH": ["ByeGzlrKwH", "r1e_FpNFDr", "rkgg6xBYDH", "SkxxtgHKPS", "HyxjOyrKvr"], "HkxCzeHFDB": ["HkxCzeHFDB", "SJlsFpVtDB", "Hklso24Kwr", "Hkg-xgrYvH", "SJxSOJStPr"], "Bkeb7lHtvH": ["Bkeb7lHtvH", "rkeNfp4tPr", "B1lLw6EYwB", "r1gixp4FPH", "rkgz2aEKDr"], "r1gfQgSFDr": ["r1gfQgSFDr", "HylsTT4FvB", "B1lPaCNtPB", "SJg7spEYDS", "HJeOekHKwr"], "BkxSmlBFvr": ["BkxSmlBFvr", "BJxH22EKPS", "H1eA7AEtvS", "H1gDNyrKDS", "HygDF6NFPB"], "rkgvXlrKwH": ["rkgvXlrKwH", "H1gX8C4YPr", "SJgVU0EKwS", "BJeGlJStPr", "Bke89JBtvB"], "H1eqQeHFDS": ["H1eqQeHFDS", "B1lDoJSYDH", "ryxmb1rKDS", "HygOjhEYDH", "S1g6xeSKDS"], "Sye57xStvB": ["Sye57xStvB", "rkg-TJBFPB", "BJewlyStDr", "BJgy96EYvr", "S1xKd24twB"], "rkeiQlBFPB": ["rkeiQlBFPB", "BklEFpEYwS", "SJeD3CEFPH", "HkgB2TNYPS", "rklp93EtwH"], "Skey4eBYPS": ["Skey4eBYPS", "HJgpugrKPS", "r1g6ogrtDr", "BJgNJgSFPS", "SylVNerFvr"], "ByexElSYDr": ["ByexElSYDr", "Bkg0u3Etwr", "BkxXe0Etwr", "rklHqRVKvH", "r1xGP6VYwH"], "B1xMEerYvB": ["B1xMEerYvB", "Bkl5kxrKDr", "S1xCPJHtDB", "Hkx7_1rKwS", "Byx_YAVYPH"], "BJgQ4lSFPH": ["BJgQ4lSFPH", "HJlWWJSFDH", "Hyl7ygStwB", "H1eA7AEtvS", "H1xPR3NtPB"], "BJg4NgBKvH": ["BJg4NgBKvH", "SkgsACVKPH", "ByxdUySKvS", "Bke89JBtvB", "HylxE1HKwS"], "SylVNerFvr": ["SylVNerFvr", "r1g6ogrtDr", "HkxTwkrKDB", "BJgNJgSFPS", "SygcCnNKwr"], "SJgwNerKvB": ["SJgwNerKvB", "r1gdj2EKPB", "H1eA7AEtvS", "SJem8lSFwB", "rJxlc0EtDr"], "HJloElBYvB": ["HJloElBYvB", "Hkxzx0NtDB", "r1g87C4KwB", "HJxMYANtPH", "BJgWE1SFwS"], "HkejNgBtPB": ["HkejNgBtPB", "B1l8L6EtDS", "S1g6xeSKDS", "S1g7tpEYDS", "BJgza6VtPB"], "r1laNeBYPB": ["r1laNeBYPB", "rkeIIkHKvS", "Bkeeca4Kvr", "r1lGO0EKDH", "r1lfF2NYvH"], "rygeHgSFDH": ["rygeHgSFDH", "SklOUpEYvB", "H1laeJrKDB", "S1g6xeSKDS", "BJxG_0EtDS"], "S1gmrxHFvB": ["S1gmrxHFvB", "ryebG04YvB", "BJlahxHYDS", "HyxJhCEFDS", "BJxI5gHKDr"], "BylQSxHFwr": ["BylQSxHFwr", "HygrdpVKvr", "BJlS634tPr", "HJxyZkBKDr", "rklTmyBKPH"], "B1l4SgHKDH": ["B1l4SgHKDH", "SJeYe0NtvH", "H1eA7AEtvS", "SJg7KhVKPH", "r1xMH1BtvB"], "BkgrBgSYDS": ["BkgrBgSYDS", "SJem8lSFwB", "HyxjOyrKvr", "HkgxW0EYDS", "rkeu30EtvS"], "rkevSgrtPr": ["rkevSgrtPr", "BkgXHTNtvS", "rkgfdeBYvH", "HklQYxBKwS", "Bylx-TNKvH"], "S1evHerYPr": ["S1evHerYPr", "SJeD3CEFPH", "BklEFpEYwS", "HkgB2TNYPS", "rklp93EtwH"], "BJxsrgStvr": ["BJxsrgStvr", "S1xnXRVFwH", "SkgsACVKPH", "BJx040EFvH", "SJgVU0EKwS"], "rygjHxrYDB": ["rygjHxrYDB", "rkeu30EtvS", "B1x1ma4tDr", "B1l6y0VFPr", "HJlSmC4FPS"], "HyxyIgHFvr": ["HyxyIgHFvr", "HJx8HANFDH", "rkllGyBFPH", "rkgg6xBYDH", "B1x6BTEKwr"], "ByglLlHFDS": ["ByglLlHFDS", "SklOUpEYvB", "SylkYeHtwr", "B1l8L6EtDS", "HkldyTNYwH"], "ryxWIgBFPS": ["ryxWIgBFPS", "HkxYzANYDB", "BklEFpEYwS", "rkeZIJBYvr", "rklp93EtwH"], "rJxGLlBtwH": ["rJxGLlBtwH", "SkxpxJBKwS", "ByxT7TNFvH", "SJxbHkrKDH", "SJgdnAVKDH"], "SJem8lSFwB": ["SJem8lSFwB", "SkgsACVKPH", "SJlbGJrtDB", "HkgxW0EYDS", "Bkxe2AVtPS"], "SJxE8erKDH": ["SJxE8erKDH", "H1x5wRVtvS", "S1l-C0NtwS", "H1laeJrKDB", "rJxycxHKDS"], "S1gEIerYwH": ["S1gEIerYwH", "rkeNfp4tPr", "BJgnXpVYwS", "HygpthEtvr", "BkeoaeHKDS"], "SJeLIgBKPS": ["SJeLIgBKPS", "BJgnXpVYwS", "rklB76EKPr", "ryeFY0EFwS", "HygpthEtvr"], "rygwLgrYPB": ["rygwLgrYPB", "r1e_FpNFDr", "ryxK0JBtPr", "rkgNKkHtvB", "BkgXHTNtvS"], "ByxaUgrFvH": ["ByxaUgrFvH", "rkxoh24FPH", "B1x62TNtDS", "rklEj2EFvB", "B1gHokBKwS"], "ByeMPlHKPH": ["ByeMPlHKPH", "r1eIiCNYwS", "ByxY8CNtvr", "rkecJ6VFvr", "SJg7KhVKPH"], "H1lNPxHKDH": ["H1lNPxHKDH", "B1guLAVFDB", "BkglSTNFDB", "rygjmpVFvB", "HygegyrYwH"], "SJxSDxrKDr": ["SJxSDxrKDr", "Skxuk1rFwB", "Hke0V1rKPS", "HJxdTxHYvB", "rklOg6EFwS"], "Bke_DertPB": ["Bke_DertPB", "HJeOekHKwr", "S1lxKlSKPH", "SJeQEp4YDH", "HkgTTh4FDH"], "rklnDgHtDS": ["rklnDgHtDS", "Hklso24Kwr", "SJxSOJStPr", "r1gdj2EKPB", "HklUCCVKDB"], "rkxawlHKDr": ["rkxawlHKDr", "SkgC6TNFvr", "B1x6BTEKwr", "B1esx6EYvr", "H1gB4RVKvB"], "BJxkOlSYDH": ["BJxkOlSYDH", "HJeTo2VFwH", "ryl3ygHYDB", "SJlbGJrtDB", "rkeu30EtvS"], "rkgfdeBYvH": ["rkgfdeBYvH", "BJlBSkHtDS", "rkllGyBFPH", "B1x6BTEKwr", "SJeLIgBKPS"], "rJe4_xSFDB": ["rJe4_xSFDB", "r1e_FpNFDr", "rkg1ngrFPr", "HklQYxBKwS", "Skxuk1rFwB"], "H1gNOeHKPS": ["H1gNOeHKPS", "rkllGyBFPH", "rkevSgrtPr", "rkxs0yHFPH", "HklSeREtPB"], "rylrdxHFDr": ["rylrdxHFDr", "HJgLLyrYwB", "S1xKd24twB", "rkgbYyHtwB", "SJg5J6NtDr"], "rkl8dlHYvB": ["rkl8dlHYvB", "SJl5Np4tPr", "SkgC6TNFvr", "rylXBkrYDS", "H1ezFREtwH"], "HJl8_eHYvS": ["HJl8_eHYvS", "S1xCPJHtDB", "r1xPh2VtPB", "rkl3m1BFDB", "HJgcvJBFvB"], "Sye_OgHFwH": ["Sye_OgHFwH", "H1xscnEKDr", "HJxdTxHYvB", "SJlHwkBYDH", "rklOg6EFwS"], "H1lK_lBtvS": ["H1lK_lBtvS", "Hyg9anEFPS", "BkgWahEFvr", "Hyl9xxHYPr", "SJl5Np4tPr"], "B1e3OlStPB": ["B1e3OlStPB", "rkecl1rtwB", "BJe-91BtvH", "H1eA7AEtvS", "BylQSxHFwr"], "HJgpugrKPS": ["HJgpugrKPS", "Skey4eBYPS", "r1g6ogrtDr", "BJgNJgSFPS", "rkeu30EtvS"], "SylkYeHtwr": ["SylkYeHtwr", "rklEj2EFvB", "B1x62TNtDS", "SklOUpEYvB", "r1eyceSYPr"], "SkxxtgHKPS": ["SkxxtgHKPS", "rkgg6xBYDH", "r1e_FpNFDr", "Hke3gyHYwH", "H1enKkrFDB"], "S1lxKlSKPH": ["S1lxKlSKPH", "B1lPaCNtPB", "Bke_DertPB", "HJeOekHKwr", "ByxdUySKvS"], "rJleKgrKwS": ["rJleKgrKwS", "rJg76kStwH", "rJxycxHKDS", "SkeuexBtDr", "SJlh8CEYDB"], "S1eZYeHFDS": ["S1eZYeHFDS", "r1egIyBFPS", "SJg7KhVKPH", "BJeKwTNFvB", "HJenn6VFvB"], "BJgMFxrYPB": ["BJgMFxrYPB", "rkg-TJBFPB", "rkl03ySYDH", "HklXn1BKDH", "HJgcvJBFvB"], "HklQYxBKwS": ["HklQYxBKwS", "HygegyrYwH", "B1guLAVFDB", "HJlxIJBFDr", "H1gBsgBYwH"], "SJxrKgStDH": ["SJxrKgStDH", "rkl03ySYDH", "BkxfaTVFwH", "HJgfDREKDB", "SkeyppEFvS"], "SyevYxHtDB": ["SyevYxHtDB", "H1xscnEKDr", "HyeaSkrYPH", "SJlHwkBYDH", "HJxdTxHYvB"], "S1xitgHtvS": ["S1xitgHtvS", "S1xKd24twB", "H1eCw3EKvH", "Bkl7bREtDr", "BJgZGeHFPH"], "SJxstlHFPH": ["SJxstlHFPH", "BJlguT4YPr", "SJgVHkrYDH", "r1eIiCNYwS", "Hyl7ygStwB"], "r1eyceSYPr": ["r1eyceSYPr", "SylkYeHtwr", "Sylgsn4Fvr", "BJgnXpVYwS", "HkxlcnVFwB"], "rJxycxHKDS": ["rJxycxHKDS", "r1gdj2EKPB", "rJleKgrKwS", "SJxE8erKDH", "rJeQoCNYDS"], "Syx79eBKwr": ["Syx79eBKwr", "rkxoh24FPH", "HJlA0C4tPS", "BJlzm64tDH", "ByxT7TNFvH"], "B1eB5xSFvr": ["B1eB5xSFvr", "HyeSin4FPB", "ryxC6kSYPr", "r1x0lxrFPS", "B1lDoJSYDH"], "BJxI5gHKDr": ["BJxI5gHKDr", "BJlahxHYDS", "BygSP6Vtvr", "ryloogSKDS", "Sklf1yrYDr"], "BkluqlSFDS": ["BkluqlSFDS", "S1xtORNFwH", "HJlnC1rKPB", "rkeu30EtvS", "HJe6uANtwH"], "S1e_9xrFvS": ["S1e_9xrFvS", "HklxbgBKvr", "SyljQyBFDH", "SJxUjlBtwB", "B1lJzyStvS"], "BJe55gBtvH": ["BJe55gBtvH", "SJgndT4KwB", "H1lj0nNFwB", "rkgfdeBYvH", "BJlBSkHtDS"], "HkxjqxBYDB": ["HkxjqxBYDB", "BJeGlJStPr", "Bkl7bREtDr", "Sye57xStvB", "BJgZGeHFPH"], "ByeWogStDS": ["ByeWogStDS", "H1ezFREtwH", "B1gqipNYwH", "ryxB2lBtvH", "ryxgJTEYDr"], "rylmoxrFDH": ["rylmoxrFDH", "HklQYxBKwS", "rkg1ngrFPr", "ryxK0JBtPr", "rJxWxxSYvB"], "H1gBsgBYwH": ["H1gBsgBYwH", "HygegyrYwH", "B1guLAVFDB", "HJlxIJBFDr", "SJxIm0VtwH"], "SJxUjlBtwB": ["SJxUjlBtwB", "HklxbgBKvr", "S1e_9xrFvS", "SkxybANtDB", "HJx81ySKwr"], "ryloogSKDS": ["ryloogSKDS", "BJxI5gHKDr", "BJlahxHYDS", "BJedHRVtPB", "SkxBUpEKwH"], "r1g6ogrtDr": ["r1g6ogrtDr", "HkxTwkrKDB", "BJgNJgSFPS", "SylVNerFvr", "Skey4eBYPS"], "SJxpsxrYPS": ["SJxpsxrYPS", "HJgK0h4Ywr", "Hyl9xxHYPr", "SygagpEKwB", "HJxK5pEYvr"], "Hyx0slrFvH": ["Hyx0slrFvH", "ryxK0JBtPr", "H1lBj2VFPS", "rkgO66VKDS", "BkgXT24tDS"], "rkg1ngrFPr": ["rkg1ngrFPr", "rkgqN1SYvr", "BJgnXpVYwS", "SJeLIgBKPS", "rJe4_xSFDB"], "rJxe3xSYDS": ["rJxe3xSYDS", "r1lOgyrKDS", "BJx040EFvH", "Hkem-lrtvH", "SJlHwkBYDH"], "HJx-3grYDB": ["HJx-3grYDB", "rklHqRVKvH", "Syx7A3NFvH", "B1gZV1HYvS", "BkxXe0Etwr"], "rylb3eBtwr": ["rylb3eBtwr", "SJx0q1rtvS", "HJgfDREKDB", "HJx81ySKwr", "HkgeGeBYDB"], "ryxB2lBtvH": ["ryxB2lBtvH", "ByeWogStDS", "B1gqipNYwH", "BJe-91BtvH", "HylxE1HKwS"], "SJx9ngStPH": ["SJx9ngStPH", "HJxyZkBKDr", "H1loF2NFwr", "rylXBkrYDS", "HygrdpVKvr"], "BJlahxHYDS": ["BJlahxHYDS", "BJxI5gHKDr", "BygSP6Vtvr", "rkxNh1Stvr", "ryloogSKDS"], "rkgg6xBYDH": ["rkgg6xBYDH", "SkxxtgHKPS", "Hke3gyHYwH", "r1e_FpNFDr", "SJgIPJBFvH"], "HyebplHYwB": ["HyebplHYwB", "HJeiDpVFPr", "HylsTT4FvB", "B1x62TNtDS", "SygcCnNKwr"], "S1erpeBFPB": ["S1erpeBFPB", "BJxH22EKPS", "HylxE1HKwS", "H1loF2NFwr", "HJxyZkBKDr"], "B1xSperKvH": ["B1xSperKvH", "rkxs0yHFPH", "SygW0TEFwH", "B1guLAVFDB", "HygegyrYwH"], "rJg8TeSFDH": ["rJg8TeSFDH", "HJx8HANFDH", "H1enKkrFDB", "SkgGjRVKDS", "HyxJhCEFDS"], "HJxdTxHYvB": ["HJxdTxHYvB", "HyeaSkrYPH", "H1xscnEKDr", "SJlHwkBYDH", "Skgy464Kvr"], "Skxd6gSYDS": ["Skxd6gSYDS", "SJxhNTNYwB", "SklTQCNtvS", "Hkem-lrtvH", "SJlHwkBYDH"], "HyeYTgrFPB": ["HyeYTgrFPB", "S1l-C0NtwS", "SJlbGJrtDB", "SygpC6Ntvr", "HJgK0h4Ywr"], "Hyg96gBKPS": ["Hyg96gBKPS", "rkecJ6VFvr", "BJg1f6EFDB", "BJxWx0NYPr", "BJlZ5ySKPH"], "BkeoaeHKDS": ["BkeoaeHKDS", "BylVcTNtDS", "ryeFY0EFwS", "BJgnXpVYwS", "S1gEIerYwH"], "S1e2agrFvS": ["S1e2agrFvS", "BylA_C4tPr", "BylEqnVFDB", "r1lGO0EKDH", "BJe8pkHFwS"], "ryxyCeHtPB": ["ryxyCeHtPB", "SkgpBJrtvS", "ByxdUySKvS", "rJxtgJBKDr", "BylVcTNtDS"]}